{
    "action_info": {
        "elem_class": "screen", 
        "elem_info": {
            "class": "screen", 
            "hash": "97XT3HEASUxQFHEsopOO2g==\n", 
            "height": 2280, 
            "hier_level": 0, 
            "human_hash": "screen_X0_Y0_W1080_H2280", 
            "index": -1, 
            "is_transformed": true, 
            "tag_name": "screen", 
            "text": "", 
            "width": 1080, 
            "x": 0, 
            "y": 0
        }, 
        "gesture": "tap", 
        "text": ""
    }, 
    "all_elems": [
        {
            "bounds": "[0,0][1080,2148]", 
            "checkable": false, 
            "checked": false, 
            "class": "android.widget.FrameLayout", 
            "clickable": false, 
            "enabled": true, 
            "focusable": false, 
            "focused": false, 
            "hash": "V8+CaTeD5lK2x+KEyC4gXA==\n", 
            "height": 2148, 
            "hier_level": 2, 
            "human_hash": "android.widget.FrameLayout_X0_Y0_W1080_H2148", 
            "index": "0", 
            "is_transformed": true, 
            "long-clickable": false, 
            "password": false, 
            "scrollable": false, 
            "selected": false, 
            "tag_name": "android.widget.FrameLayout", 
            "text": "", 
            "width": 1080, 
            "x": 0, 
            "y": 0
        }, 
        {
            "bounds": "[0,0][1080,2148]", 
            "checkable": false, 
            "checked": false, 
            "class": "android.view.ViewGroup", 
            "clickable": false, 
            "enabled": true, 
            "focusable": false, 
            "focused": false, 
            "hash": "gnhQAw/RJ5mpmi/SzlPK3Q==\n", 
            "height": 2148, 
            "hier_level": 3, 
            "human_hash": "android.view.ViewGroup_X0_Y0_W1080_H2148", 
            "index": "0", 
            "is_transformed": true, 
            "long-clickable": false, 
            "password": false, 
            "resource-id": "android:id/decor_content_parent", 
            "scrollable": false, 
            "selected": false, 
            "tag_name": "android.view.ViewGroup", 
            "text": "", 
            "width": 1080, 
            "x": 0, 
            "y": 0
        }, 
        {
            "bounds": "[0,0][1080,2148]", 
            "checkable": false, 
            "checked": false, 
            "class": "android.widget.FrameLayout", 
            "clickable": false, 
            "enabled": true, 
            "focusable": false, 
            "focused": false, 
            "hash": "V8+CaTeD5lK2x+KEyC4gXA==\n", 
            "height": 2148, 
            "hier_level": 4, 
            "human_hash": "android.widget.FrameLayout_X0_Y0_W1080_H2148", 
            "index": "0", 
            "is_transformed": true, 
            "long-clickable": false, 
            "password": false, 
            "resource-id": "android:id/content", 
            "scrollable": false, 
            "selected": false, 
            "tag_name": "android.widget.FrameLayout", 
            "text": "", 
            "width": 1080, 
            "x": 0, 
            "y": 0
        }, 
        {
            "bounds": "[0,0][1080,2148]", 
            "checkable": false, 
            "checked": false, 
            "class": "android.widget.FrameLayout", 
            "clickable": false, 
            "enabled": true, 
            "focusable": false, 
            "focused": false, 
            "hash": "V8+CaTeD5lK2x+KEyC4gXA==\n", 
            "height": 2148, 
            "hier_level": 5, 
            "human_hash": "android.widget.FrameLayout_X0_Y0_W1080_H2148", 
            "index": "0", 
            "is_transformed": true, 
            "long-clickable": false, 
            "password": false, 
            "resource-id": "com.android.camera2:id/activity_root_view", 
            "scrollable": false, 
            "selected": false, 
            "tag_name": "android.widget.FrameLayout", 
            "text": "", 
            "width": 1080, 
            "x": 0, 
            "y": 0
        }, 
        {
            "bounds": "[0,0][1080,2148]", 
            "checkable": false, 
            "checked": false, 
            "class": "android.widget.FrameLayout", 
            "clickable": false, 
            "enabled": true, 
            "focusable": false, 
            "focused": false, 
            "hash": "V8+CaTeD5lK2x+KEyC4gXA==\n", 
            "height": 2148, 
            "hier_level": 6, 
            "human_hash": "android.widget.FrameLayout_X0_Y0_W1080_H2148", 
            "index": "0", 
            "is_transformed": true, 
            "long-clickable": false, 
            "password": false, 
            "resource-id": "com.android.camera2:id/camera_app_root", 
            "scrollable": false, 
            "selected": false, 
            "tag_name": "android.widget.FrameLayout", 
            "text": "", 
            "width": 1080, 
            "x": 0, 
            "y": 0
        }, 
        {
            "bounds": "[0,0][1080,2148]", 
            "checkable": false, 
            "checked": false, 
            "class": "android.view.View", 
            "clickable": false, 
            "enabled": true, 
            "focusable": false, 
            "focused": false, 
            "hash": "E34pWM/h2JuwrMqj16u8Jw==\n", 
            "height": 2148, 
            "hier_level": 7, 
            "human_hash": "android.view.View_X0_Y0_W1080_H2148", 
            "index": "0", 
            "is_transformed": true, 
            "long-clickable": false, 
            "password": false, 
            "resource-id": "com.android.camera2:id/preview_content", 
            "scrollable": false, 
            "selected": false, 
            "tag_name": "android.view.View", 
            "text": "", 
            "width": 1080, 
            "x": 0, 
            "y": 0
        }, 
        {
            "bounds": "[0,0][1080,2148]", 
            "checkable": false, 
            "checked": false, 
            "class": "android.view.View", 
            "clickable": false, 
            "enabled": true, 
            "focusable": false, 
            "focused": false, 
            "hash": "E34pWM/h2JuwrMqj16u8Jw==\n", 
            "height": 2148, 
            "hier_level": 7, 
            "human_hash": "android.view.View_X0_Y0_W1080_H2148", 
            "index": "1", 
            "is_transformed": true, 
            "long-clickable": false, 
            "password": false, 
            "resource-id": "com.android.camera2:id/focus_ring", 
            "scrollable": false, 
            "selected": false, 
            "tag_name": "android.view.View", 
            "text": "", 
            "width": 1080, 
            "x": 0, 
            "y": 0
        }, 
        {
            "bounds": "[0,0][1080,2148]", 
            "checkable": false, 
            "checked": false, 
            "class": "android.view.View", 
            "clickable": false, 
            "enabled": true, 
            "focusable": false, 
            "focused": false, 
            "hash": "E34pWM/h2JuwrMqj16u8Jw==\n", 
            "height": 2148, 
            "hier_level": 7, 
            "human_hash": "android.view.View_X0_Y0_W1080_H2148", 
            "index": "2", 
            "is_transformed": true, 
            "long-clickable": false, 
            "password": false, 
            "resource-id": "com.android.camera2:id/preview_overlay", 
            "scrollable": false, 
            "selected": false, 
            "tag_name": "android.view.View", 
            "text": "", 
            "width": 1080, 
            "x": 0, 
            "y": 0
        }, 
        {
            "bounds": "[0,0][1080,2148]", 
            "checkable": false, 
            "checked": false, 
            "class": "android.view.View", 
            "clickable": false, 
            "enabled": true, 
            "focusable": false, 
            "focused": false, 
            "hash": "E34pWM/h2JuwrMqj16u8Jw==\n", 
            "height": 2148, 
            "hier_level": 7, 
            "human_hash": "android.view.View_X0_Y0_W1080_H2148", 
            "index": "3", 
            "is_transformed": true, 
            "long-clickable": false, 
            "password": false, 
            "resource-id": "com.android.camera2:id/face_view", 
            "scrollable": false, 
            "selected": false, 
            "tag_name": "android.view.View", 
            "text": "", 
            "width": 1080, 
            "x": 0, 
            "y": 0
        }, 
        {
            "bounds": "[0,0][1080,2148]", 
            "checkable": false, 
            "checked": false, 
            "class": "android.widget.FrameLayout", 
            "clickable": false, 
            "enabled": true, 
            "focusable": false, 
            "focused": false, 
            "hash": "V8+CaTeD5lK2x+KEyC4gXA==\n", 
            "height": 2148, 
            "hier_level": 7, 
            "human_hash": "android.widget.FrameLayout_X0_Y0_W1080_H2148", 
            "index": "4", 
            "is_transformed": true, 
            "long-clickable": false, 
            "password": false, 
            "resource-id": "com.android.camera2:id/module_layout", 
            "scrollable": false, 
            "selected": false, 
            "tag_name": "android.widget.FrameLayout", 
            "text": "", 
            "width": 1080, 
            "x": 0, 
            "y": 0
        }, 
        {
            "bounds": "[0,0][1080,2148]", 
            "checkable": false, 
            "checked": false, 
            "class": "android.widget.ImageView", 
            "clickable": false, 
            "enabled": true, 
            "focusable": false, 
            "focused": false, 
            "hash": "OwvUYDN+yZ/hZLEoRPij1A==\n", 
            "height": 2148, 
            "hier_level": 8, 
            "human_hash": "android.widget.ImageView_X0_Y0_W1080_H2148", 
            "index": "0", 
            "is_transformed": true, 
            "long-clickable": false, 
            "password": false, 
            "resource-id": "com.android.camera2:id/review_image", 
            "scrollable": false, 
            "selected": false, 
            "tag_name": "android.widget.ImageView", 
            "text": "", 
            "width": 1080, 
            "x": 0, 
            "y": 0
        }, 
        {
            "bounds": "[36,36][1044,2016]", 
            "checkable": false, 
            "checked": false, 
            "class": "android.view.ViewGroup", 
            "clickable": false, 
            "enabled": true, 
            "focusable": false, 
            "focused": false, 
            "hash": "pVJWcv1YmZyzHHp8SAF2rg==\n", 
            "height": 1980, 
            "hier_level": 8, 
            "human_hash": "android.view.ViewGroup_X36_Y36_W1008_H1980", 
            "index": "1", 
            "is_transformed": true, 
            "long-clickable": false, 
            "password": false, 
            "resource-id": "com.android.camera2:id/recording_time_rect", 
            "scrollable": false, 
            "selected": false, 
            "tag_name": "android.view.ViewGroup", 
            "text": "", 
            "width": 1008, 
            "x": 36, 
            "y": 36
        }, 
        {
            "bounds": "[36,36][1044,2016]", 
            "checkable": false, 
            "checked": false, 
            "class": "android.widget.LinearLayout", 
            "clickable": false, 
            "enabled": true, 
            "focusable": false, 
            "focused": false, 
            "hash": "Bb+Y9+JB5aQ9GtAixwZoLw==\n", 
            "height": 1980, 
            "hier_level": 9, 
            "human_hash": "android.widget.LinearLayout_X36_Y36_W1008_H1980", 
            "index": "0", 
            "is_transformed": true, 
            "long-clickable": false, 
            "password": false, 
            "resource-id": "com.android.camera2:id/labels", 
            "scrollable": false, 
            "selected": false, 
            "tag_name": "android.widget.LinearLayout", 
            "text": "", 
            "width": 1008, 
            "x": 36, 
            "y": 36
        }, 
        {
            "bounds": "[0,0][1080,2148]", 
            "checkable": false, 
            "checked": false, 
            "class": "android.widget.FrameLayout", 
            "clickable": false, 
            "enabled": true, 
            "focusable": false, 
            "focused": false, 
            "hash": "V8+CaTeD5lK2x+KEyC4gXA==\n", 
            "height": 2148, 
            "hier_level": 7, 
            "human_hash": "android.widget.FrameLayout_X0_Y0_W1080_H2148", 
            "index": "5", 
            "is_transformed": true, 
            "long-clickable": false, 
            "password": false, 
            "resource-id": "com.android.camera2:id/sticky_bottom_capture_layout", 
            "scrollable": false, 
            "selected": false, 
            "tag_name": "android.widget.FrameLayout", 
            "text": "", 
            "width": 1080, 
            "x": 0, 
            "y": 0
        }, 
        {
            "bounds": "[885,1524][1077,1716]", 
            "checkable": false, 
            "checked": false, 
            "class": "android.view.View", 
            "clickable": true, 
            "enabled": true, 
            "focusable": true, 
            "focused": false, 
            "hash": "ST+lsode/buk0iKQlBQBaw==\n", 
            "height": 192, 
            "hier_level": 8, 
            "human_hash": "android.view.View_X885_Y1524_W192_H192", 
            "index": "0", 
            "is_transformed": true, 
            "long-clickable": false, 
            "password": false, 
            "resource-id": "com.android.camera2:id/rounded_thumbnail_view", 
            "scrollable": false, 
            "selected": false, 
            "tag_name": "android.view.View", 
            "text": "", 
            "width": 192, 
            "x": 885, 
            "y": 1524
        }, 
        {
            "bounds": "[0,1884][1080,2148]", 
            "checkable": false, 
            "checked": false, 
            "class": "android.widget.FrameLayout", 
            "clickable": false, 
            "enabled": true, 
            "focusable": false, 
            "focused": false, 
            "hash": "Ga03Y7HuhGlNZw5O/u4UFA==\n", 
            "height": 264, 
            "hier_level": 8, 
            "human_hash": "android.widget.FrameLayout_X0_Y1884_W1080_H264", 
            "index": "1", 
            "is_transformed": true, 
            "long-clickable": false, 
            "password": false, 
            "resource-id": "com.android.camera2:id/bottom_bar", 
            "scrollable": false, 
            "selected": false, 
            "tag_name": "android.widget.FrameLayout", 
            "text": "", 
            "width": 1080, 
            "x": 0, 
            "y": 1884
        }, 
        {
            "bounds": "[0,1884][1080,2148]", 
            "checkable": false, 
            "checked": false, 
            "class": "android.widget.LinearLayout", 
            "clickable": false, 
            "enabled": true, 
            "focusable": false, 
            "focused": false, 
            "hash": "Z6EwuN67dc1CObsyd+4HvQ==\n", 
            "height": 264, 
            "hier_level": 9, 
            "human_hash": "android.widget.LinearLayout_X0_Y1884_W1080_H264", 
            "index": "0", 
            "is_transformed": true, 
            "long-clickable": false, 
            "password": false, 
            "resource-id": "com.android.camera2:id/bottombar_intent_review", 
            "scrollable": false, 
            "selected": false, 
            "tag_name": "android.widget.LinearLayout", 
            "text": "", 
            "width": 1080, 
            "x": 0, 
            "y": 1884
        }, 
        {
            "bounds": "[0,1884][264,2148]", 
            "checkable": false, 
            "checked": false, 
            "class": "android.widget.ImageButton", 
            "clickable": true, 
            "content-desc": "Review", 
            "enabled": true, 
            "focusable": true, 
            "focused": false, 
            "hash": "/vNOEVaZ3lJEsEbQuSyjkg==\n", 
            "height": 264, 
            "hier_level": 10, 
            "human_hash": "android.widget.ImageButton_X0_Y1884_W264_H264", 
            "index": "0", 
            "is_transformed": true, 
            "long-clickable": false, 
            "password": false, 
            "resource-id": "com.android.camera2:id/retake_button", 
            "scrollable": false, 
            "selected": false, 
            "tag_name": "android.widget.ImageButton", 
            "text": "", 
            "width": 264, 
            "x": 0, 
            "y": 1884
        }, 
        {
            "bounds": "[264,1900][860,2131]", 
            "checkable": false, 
            "checked": false, 
            "class": "android.widget.FrameLayout", 
            "clickable": false, 
            "enabled": true, 
            "focusable": false, 
            "focused": false, 
            "hash": "UHR+HLRoKSuNE4gRFaOW1w==\n", 
            "height": 231, 
            "hier_level": 10, 
            "human_hash": "android.widget.FrameLayout_X264_Y1900_W596_H231", 
            "index": "1", 
            "is_transformed": true, 
            "long-clickable": false, 
            "password": false, 
            "scrollable": false, 
            "selected": false, 
            "tag_name": "android.widget.FrameLayout", 
            "text": "", 
            "width": 596, 
            "x": 264, 
            "y": 1900
        }, 
        {
            "bounds": "[446,1900][677,2131]", 
            "checkable": false, 
            "checked": false, 
            "class": "android.widget.ImageButton", 
            "clickable": true, 
            "content-desc": "Done", 
            "enabled": true, 
            "focusable": true, 
            "focused": false, 
            "hash": "o1OOr5+8wAp9kt5n5HMsXg==\n", 
            "height": 231, 
            "hier_level": 11, 
            "human_hash": "android.widget.ImageButton_X446_Y1900_W231_H231", 
            "index": "0", 
            "is_transformed": true, 
            "long-clickable": false, 
            "password": false, 
            "resource-id": "com.android.camera2:id/done_button", 
            "scrollable": false, 
            "selected": false, 
            "tag_name": "android.widget.ImageButton", 
            "text": "", 
            "width": 231, 
            "x": 446, 
            "y": 1900
        }, 
        {
            "bounds": "[860,1906][1080,2126]", 
            "checkable": false, 
            "checked": false, 
            "class": "android.widget.ImageButton", 
            "clickable": true, 
            "content-desc": "Cancel", 
            "enabled": true, 
            "focusable": true, 
            "focused": false, 
            "hash": "L20qcQl3R1uKbuNL6YuDRg==\n", 
            "height": 220, 
            "hier_level": 10, 
            "human_hash": "android.widget.ImageButton_X860_Y1906_W220_H220", 
            "index": "2", 
            "is_transformed": true, 
            "long-clickable": false, 
            "password": false, 
            "resource-id": "com.android.camera2:id/cancel_button", 
            "scrollable": false, 
            "selected": false, 
            "tag_name": "android.widget.ImageButton", 
            "text": "", 
            "width": 220, 
            "x": 860, 
            "y": 1906
        }
    ], 
    "cpu": 0, 
    "jank": 0, 
    "mem": 0, 
    "net": 0, 
    "processed": false, 
    "timing": 0
}