{
    "action_info": {
        "elem_class": "screen", 
        "elem_info": {
            "class": "screen", 
            "hash": "97XT3HEASUxQFHEsopOO2g==\n", 
            "height": 2280, 
            "hier_level": 0, 
            "human_hash": "screen_X0_Y0_W1080_H2280", 
            "index": -1, 
            "is_transformed": true, 
            "tag_name": "screen", 
            "text": "", 
            "width": 1080, 
            "x": 0, 
            "y": 0
        }, 
        "gesture": "no_op", 
        "text": "no_op"
    }, 
    "all_elems": [
        {
            "bounds": "[0,0][1080,2236]", 
            "checkable": false, 
            "checked": false, 
            "class": "android.widget.FrameLayout", 
            "clickable": false, 
            "enabled": true, 
            "focusable": false, 
            "focused": false, 
            "hash": "96BC2T8MrwjFDjABqqxGFw==\n", 
            "height": 2236, 
            "hier_level": 2, 
            "human_hash": "android.widget.FrameLayout_X0_Y0_W1080_H2236", 
            "index": "0", 
            "is_transformed": true, 
            "long-clickable": false, 
            "password": false, 
            "scrollable": false, 
            "selected": false, 
            "tag_name": "android.widget.FrameLayout", 
            "text": "Search FREE netflix.com/deathto2020 Watch Now Vote 0 Share r/LssAutomation Posted by u/lss_bvt_ios_08   5h LssTest-TextPost-47038 1 Comment Mod Top broadcast Live 4,762 watching Naptime for Valentine LssLiveChat-TextPost LssLiveChat-TextPost 2 1,188", 
            "width": 1080, 
            "x": 0, 
            "y": 0
        }, 
        {
            "bounds": "[0,0][1080,2236]", 
            "checkable": false, 
            "checked": false, 
            "class": "android.widget.LinearLayout", 
            "clickable": false, 
            "enabled": true, 
            "focusable": false, 
            "focused": false, 
            "hash": "ngfqQiFsupZh69hUMYltRg==\n", 
            "height": 2236, 
            "hier_level": 3, 
            "human_hash": "android.widget.LinearLayout_X0_Y0_W1080_H2236", 
            "index": "0", 
            "is_transformed": true, 
            "long-clickable": false, 
            "password": false, 
            "scrollable": false, 
            "selected": false, 
            "tag_name": "android.widget.LinearLayout", 
            "text": "Search FREE netflix.com/deathto2020 Watch Now Vote 0 Share r/LssAutomation Posted by u/lss_bvt_ios_08   5h LssTest-TextPost-47038 1 Comment Mod Top broadcast Live 4,762 watching Naptime for Valentine LssLiveChat-TextPost LssLiveChat-TextPost 2 1,188", 
            "width": 1080, 
            "x": 0, 
            "y": 0
        }, 
        {
            "bounds": "[0,0][1080,2236]", 
            "checkable": false, 
            "checked": false, 
            "class": "android.widget.FrameLayout", 
            "clickable": false, 
            "enabled": true, 
            "focusable": false, 
            "focused": false, 
            "hash": "96BC2T8MrwjFDjABqqxGFw==\n", 
            "height": 2236, 
            "hier_level": 4, 
            "human_hash": "android.widget.FrameLayout_X0_Y0_W1080_H2236", 
            "index": "0", 
            "is_transformed": true, 
            "long-clickable": false, 
            "password": false, 
            "scrollable": false, 
            "selected": false, 
            "tag_name": "android.widget.FrameLayout", 
            "text": "Search FREE netflix.com/deathto2020 Watch Now Vote 0 Share r/LssAutomation Posted by u/lss_bvt_ios_08   5h LssTest-TextPost-47038 1 Comment Mod Top broadcast Live 4,762 watching Naptime for Valentine LssLiveChat-TextPost LssLiveChat-TextPost 2 1,188", 
            "width": 1080, 
            "x": 0, 
            "y": 0
        }, 
        {
            "bounds": "[0,0][1080,2236]", 
            "checkable": false, 
            "checked": false, 
            "class": "android.widget.FrameLayout", 
            "clickable": false, 
            "enabled": true, 
            "focusable": false, 
            "focused": false, 
            "hash": "96BC2T8MrwjFDjABqqxGFw==\n", 
            "height": 2236, 
            "hier_level": 5, 
            "human_hash": "android.widget.FrameLayout_X0_Y0_W1080_H2236", 
            "index": "0", 
            "is_transformed": true, 
            "long-clickable": false, 
            "password": false, 
            "resource-id": "com.reddit.frontpage.alpha:id/action_bar_root", 
            "scrollable": false, 
            "selected": false, 
            "tag_name": "android.widget.FrameLayout", 
            "text": "Search FREE netflix.com/deathto2020 Watch Now Vote 0 Share r/LssAutomation Posted by u/lss_bvt_ios_08   5h LssTest-TextPost-47038 1 Comment Mod Top broadcast Live 4,762 watching Naptime for Valentine LssLiveChat-TextPost LssLiveChat-TextPost 2 1,188", 
            "width": 1080, 
            "x": 0, 
            "y": 0
        }, 
        {
            "bounds": "[0,0][1080,2236]", 
            "checkable": false, 
            "checked": false, 
            "class": "android.widget.FrameLayout", 
            "clickable": false, 
            "enabled": true, 
            "focusable": false, 
            "focused": false, 
            "hash": "96BC2T8MrwjFDjABqqxGFw==\n", 
            "height": 2236, 
            "hier_level": 6, 
            "human_hash": "android.widget.FrameLayout_X0_Y0_W1080_H2236", 
            "index": "0", 
            "is_transformed": true, 
            "long-clickable": false, 
            "password": false, 
            "resource-id": "android:id/content", 
            "scrollable": false, 
            "selected": false, 
            "tag_name": "android.widget.FrameLayout", 
            "text": "Search FREE netflix.com/deathto2020 Watch Now Vote 0 Share r/LssAutomation Posted by u/lss_bvt_ios_08   5h LssTest-TextPost-47038 1 Comment Mod Top broadcast Live 4,762 watching Naptime for Valentine LssLiveChat-TextPost LssLiveChat-TextPost 2 1,188", 
            "width": 1080, 
            "x": 0, 
            "y": 0
        }, 
        {
            "bounds": "[0,0][1080,2236]", 
            "checkable": false, 
            "checked": false, 
            "class": "androidx.drawerlayout.widget.DrawerLayout", 
            "clickable": false, 
            "enabled": true, 
            "focusable": false, 
            "focused": false, 
            "hash": "8TWHpotFaHZXqowdhCD6WQ==\n", 
            "height": 2236, 
            "hier_level": 7, 
            "human_hash": "androidx.drawerlayout.widget.DrawerLayout_X0_Y0_W1080_H2236", 
            "index": "0", 
            "is_transformed": true, 
            "long-clickable": false, 
            "password": false, 
            "resource-id": "com.reddit.frontpage.alpha:id/drawer_layout", 
            "scrollable": false, 
            "selected": false, 
            "tag_name": "androidx.drawerlayout.widget.DrawerLayout", 
            "text": "Search FREE netflix.com/deathto2020 Watch Now Vote 0 Share r/LssAutomation Posted by u/lss_bvt_ios_08   5h LssTest-TextPost-47038 1 Comment Mod Top broadcast Live 4,762 watching Naptime for Valentine LssLiveChat-TextPost LssLiveChat-TextPost 2 1,188", 
            "width": 1080, 
            "x": 0, 
            "y": 0
        }, 
        {
            "bounds": "[0,0][1080,2236]", 
            "checkable": false, 
            "checked": false, 
            "class": "android.view.ViewGroup", 
            "clickable": false, 
            "enabled": true, 
            "focusable": false, 
            "focused": false, 
            "hash": "IsTXKYArhh53b3zsKQ0c0Q==\n", 
            "height": 2236, 
            "hier_level": 8, 
            "human_hash": "android.view.ViewGroup_X0_Y0_W1080_H2236", 
            "index": "0", 
            "is_transformed": true, 
            "long-clickable": false, 
            "password": false, 
            "scrollable": false, 
            "selected": false, 
            "tag_name": "android.view.ViewGroup", 
            "text": "Search FREE netflix.com/deathto2020 Watch Now Vote 0 Share r/LssAutomation Posted by u/lss_bvt_ios_08   5h LssTest-TextPost-47038 1 Comment Mod Top broadcast Live 4,762 watching Naptime for Valentine LssLiveChat-TextPost LssLiveChat-TextPost 2 1,188", 
            "width": 1080, 
            "x": 0, 
            "y": 0
        }, 
        {
            "bounds": "[0,0][1080,2236]", 
            "checkable": false, 
            "checked": false, 
            "class": "android.widget.FrameLayout", 
            "clickable": false, 
            "enabled": true, 
            "focusable": false, 
            "focused": false, 
            "hash": "96BC2T8MrwjFDjABqqxGFw==\n", 
            "height": 2236, 
            "hier_level": 9, 
            "human_hash": "android.widget.FrameLayout_X0_Y0_W1080_H2236", 
            "index": "0", 
            "is_transformed": true, 
            "long-clickable": false, 
            "password": false, 
            "resource-id": "com.reddit.frontpage.alpha:id/controller_container", 
            "scrollable": false, 
            "selected": false, 
            "tag_name": "android.widget.FrameLayout", 
            "text": "Search FREE netflix.com/deathto2020 Watch Now Vote 0 Share r/LssAutomation Posted by u/lss_bvt_ios_08   5h LssTest-TextPost-47038 1 Comment Mod Top broadcast Live 4,762 watching Naptime for Valentine LssLiveChat-TextPost LssLiveChat-TextPost 2 1,188", 
            "width": 1080, 
            "x": 0, 
            "y": 0
        }, 
        {
            "bounds": "[0,0][1080,2236]", 
            "checkable": false, 
            "checked": false, 
            "class": "android.view.ViewGroup", 
            "clickable": false, 
            "enabled": true, 
            "focusable": false, 
            "focused": false, 
            "hash": "IsTXKYArhh53b3zsKQ0c0Q==\n", 
            "height": 2236, 
            "hier_level": 10, 
            "human_hash": "android.view.ViewGroup_X0_Y0_W1080_H2236", 
            "index": "0", 
            "is_transformed": true, 
            "long-clickable": false, 
            "password": false, 
            "scrollable": false, 
            "selected": false, 
            "tag_name": "android.view.ViewGroup", 
            "text": "Search FREE netflix.com/deathto2020 Watch Now Vote 0 Share r/LssAutomation Posted by u/lss_bvt_ios_08   5h LssTest-TextPost-47038 1 Comment Mod Top broadcast Live 4,762 watching Naptime for Valentine LssLiveChat-TextPost LssLiveChat-TextPost 2 1,188", 
            "width": 1080, 
            "x": 0, 
            "y": 0
        }, 
        {
            "bounds": "[0,0][1080,2236]", 
            "checkable": false, 
            "checked": false, 
            "class": "android.widget.FrameLayout", 
            "clickable": false, 
            "enabled": true, 
            "focusable": false, 
            "focused": false, 
            "hash": "JTZngWd2PhNmcwjywmpxAw==\n", 
            "height": 2236, 
            "hier_level": 11, 
            "human_hash": "android.widget.FrameLayout_X0_Y0_W1080_H2236", 
            "index": "0", 
            "is_transformed": true, 
            "long-clickable": false, 
            "password": false, 
            "resource-id": "com.reddit.frontpage.alpha:id/container", 
            "scrollable": false, 
            "selected": false, 
            "tag_name": "android.widget.FrameLayout", 
            "text": "Search FREE netflix.com/deathto2020 Watch Now Vote 0 Share r/LssAutomation Posted by u/lss_bvt_ios_08   5h LssTest-TextPost-47038 1 Comment Mod Top broadcast Live 4,762 watching Naptime for Valentine LssLiveChat-TextPost LssLiveChat-TextPost", 
            "width": 1080, 
            "x": 0, 
            "y": 0
        }, 
        {
            "bounds": "[0,0][1080,2093]", 
            "checkable": false, 
            "checked": false, 
            "class": "android.widget.LinearLayout", 
            "clickable": false, 
            "enabled": true, 
            "focusable": false, 
            "focused": false, 
            "hash": "9lF5Q/v0KDrYALj3IqVGTg==\n", 
            "height": 2093, 
            "hier_level": 12, 
            "human_hash": "android.widget.LinearLayout_X0_Y0_W1080_H2093", 
            "index": "0", 
            "is_transformed": true, 
            "long-clickable": false, 
            "password": false, 
            "scrollable": false, 
            "selected": false, 
            "tag_name": "android.widget.LinearLayout", 
            "text": "Search FREE netflix.com/deathto2020 Watch Now Vote 0 Share r/LssAutomation Posted by u/lss_bvt_ios_08   5h LssTest-TextPost-47038 1 Comment Mod Top broadcast Live 4,762 watching Naptime for Valentine LssLiveChat-TextPost LssLiveChat-TextPost", 
            "width": 1080, 
            "x": 0, 
            "y": 0
        }, 
        {
            "bounds": "[0,0][1080,237]", 
            "checkable": false, 
            "checked": false, 
            "class": "android.view.ViewGroup", 
            "clickable": false, 
            "enabled": true, 
            "focusable": false, 
            "focused": false, 
            "hash": "nlyKt1/NExUO1jM/PVMCfA==\n", 
            "height": 237, 
            "hier_level": 13, 
            "human_hash": "android.view.ViewGroup_X0_Y0_W1080_H237", 
            "index": "0", 
            "is_transformed": true, 
            "long-clickable": false, 
            "password": false, 
            "resource-id": "com.reddit.frontpage.alpha:id/toolbar", 
            "scrollable": false, 
            "selected": false, 
            "tag_name": "android.view.ViewGroup", 
            "text": "Search FREE", 
            "width": 1080, 
            "x": 0, 
            "y": 0
        }, 
        {
            "bounds": "[0,110][1080,209]", 
            "checkable": false, 
            "checked": false, 
            "class": "android.widget.LinearLayout", 
            "clickable": false, 
            "enabled": true, 
            "focusable": false, 
            "focused": false, 
            "hash": "fBox8GbYhxd6eNyPkw8Yvw==\n", 
            "height": 99, 
            "hier_level": 14, 
            "human_hash": "android.widget.LinearLayout_X0_Y110_W1080_H99", 
            "index": "0", 
            "is_transformed": true, 
            "long-clickable": false, 
            "password": false, 
            "resource-id": "com.reddit.frontpage.alpha:id/toolbar_nav_search", 
            "scrollable": false, 
            "selected": false, 
            "tag_name": "android.widget.LinearLayout", 
            "text": "Search FREE", 
            "width": 1080, 
            "x": 0, 
            "y": 110
        }, 
        {
            "bounds": "[0,110][154,209]", 
            "checkable": false, 
            "checked": false, 
            "class": "android.widget.FrameLayout", 
            "clickable": false, 
            "enabled": true, 
            "focusable": false, 
            "focused": false, 
            "hash": "TswSllakcCKuypPS0W/JVA==\n", 
            "height": 99, 
            "hier_level": 15, 
            "human_hash": "android.widget.FrameLayout_X0_Y110_W154_H99", 
            "index": "0", 
            "is_transformed": true, 
            "long-clickable": false, 
            "password": false, 
            "resource-id": "com.reddit.frontpage.alpha:id/nav_icon_container", 
            "scrollable": false, 
            "selected": false, 
            "tag_name": "android.widget.FrameLayout", 
            "text": "", 
            "width": 154, 
            "x": 0, 
            "y": 110
        }, 
        {
            "bounds": "[0,110][154,209]", 
            "checkable": false, 
            "checked": false, 
            "class": "android.view.View", 
            "clickable": true, 
            "enabled": true, 
            "focusable": true, 
            "focused": false, 
            "hash": "5hPtgp/O5OPsp86fbLtgdw==\n", 
            "height": 99, 
            "hier_level": 16, 
            "human_hash": "android.view.View_X0_Y110_W154_H99", 
            "index": "0", 
            "is_transformed": true, 
            "long-clickable": true, 
            "password": false, 
            "resource-id": "com.reddit.frontpage.alpha:id/nav_icon_clickable_area", 
            "scrollable": false, 
            "selected": false, 
            "tag_name": "android.view.View", 
            "text": "", 
            "width": 154, 
            "x": 0, 
            "y": 110
        }, 
        {
            "bounds": "[44,126][110,192]", 
            "checkable": false, 
            "checked": false, 
            "class": "android.widget.FrameLayout", 
            "clickable": false, 
            "content-desc": "Logged in avatar", 
            "enabled": true, 
            "focusable": false, 
            "focused": false, 
            "hash": "8tVpKulusMfy/K8N7A4y2A==\n", 
            "height": 66, 
            "hier_level": 16, 
            "human_hash": "android.widget.FrameLayout_X44_Y126_W66_H66", 
            "index": "1", 
            "is_transformed": true, 
            "long-clickable": false, 
            "password": false, 
            "resource-id": "com.reddit.frontpage.alpha:id/nav_icon", 
            "scrollable": false, 
            "selected": false, 
            "tag_name": "android.widget.FrameLayout", 
            "text": "", 
            "width": 66, 
            "x": 44, 
            "y": 126
        }, 
        {
            "bounds": "[44,126][110,192]", 
            "checkable": false, 
            "checked": false, 
            "class": "android.widget.ImageView", 
            "clickable": false, 
            "enabled": true, 
            "focusable": false, 
            "focused": false, 
            "hash": "dWazRCXN8bUIcoQl8CW5pQ==\n", 
            "height": 66, 
            "hier_level": 17, 
            "human_hash": "android.widget.ImageView_X44_Y126_W66_H66", 
            "index": "0", 
            "is_transformed": true, 
            "long-clickable": false, 
            "password": false, 
            "resource-id": "com.reddit.frontpage.alpha:id/inner_avatar", 
            "scrollable": false, 
            "selected": false, 
            "tag_name": "android.widget.ImageView", 
            "text": "", 
            "width": 66, 
            "x": 44, 
            "y": 126
        }, 
        {
            "bounds": "[154,110][948,209]", 
            "checkable": false, 
            "checked": false, 
            "class": "android.widget.TextView", 
            "clickable": true, 
            "enabled": true, 
            "focusable": true, 
            "focused": false, 
            "hash": "FYfk1t6naj1z1U4bFXfHbQ==\n", 
            "height": 99, 
            "hier_level": 15, 
            "human_hash": "android.widget.TextView_X154_Y110_W794_H99", 
            "index": "1", 
            "is_transformed": true, 
            "long-clickable": false, 
            "password": false, 
            "resource-id": "com.reddit.frontpage.alpha:id/search_view", 
            "scrollable": false, 
            "selected": false, 
            "tag_name": "android.widget.TextView", 
            "text": "Search", 
            "width": 794, 
            "x": 154, 
            "y": 110
        }, 
        {
            "bounds": "[970,114][1080,205]", 
            "checkable": false, 
            "checked": false, 
            "class": "android.widget.LinearLayout", 
            "clickable": true, 
            "enabled": true, 
            "focusable": true, 
            "focused": false, 
            "hash": "Pjm0AAQdfOMxarCYiWdoEw==\n", 
            "height": 91, 
            "hier_level": 15, 
            "human_hash": "android.widget.LinearLayout_X970_Y114_W110_H91", 
            "index": "2", 
            "is_transformed": true, 
            "long-clickable": false, 
            "password": false, 
            "scrollable": false, 
            "selected": false, 
            "tag_name": "android.widget.LinearLayout", 
            "text": "FREE", 
            "width": 110, 
            "x": 970, 
            "y": 114
        }, 
        {
            "bounds": "[970,114][1058,202]", 
            "checkable": false, 
            "checked": false, 
            "class": "android.widget.ImageView", 
            "clickable": false, 
            "content-desc": "Get Coins", 
            "enabled": true, 
            "focusable": false, 
            "focused": false, 
            "hash": "9P1fA77vo3xm6fQn0588fQ==\n", 
            "height": 88, 
            "hier_level": 16, 
            "human_hash": "android.widget.ImageView_X970_Y114_W88_H88", 
            "index": "0", 
            "is_transformed": true, 
            "long-clickable": false, 
            "password": false, 
            "scrollable": false, 
            "selected": false, 
            "tag_name": "android.widget.ImageView", 
            "text": "", 
            "width": 88, 
            "x": 970, 
            "y": 114
        }, 
        {
            "bounds": "[970,172][1058,205]", 
            "checkable": false, 
            "checked": false, 
            "class": "android.widget.TextView", 
            "clickable": false, 
            "enabled": true, 
            "focusable": false, 
            "focused": false, 
            "hash": "SkQ39yEdpaMykJkX3YXg0w==\n", 
            "height": 33, 
            "hier_level": 16, 
            "human_hash": "android.widget.TextView_X970_Y172_W88_H33", 
            "index": "1", 
            "is_transformed": true, 
            "long-clickable": false, 
            "password": false, 
            "resource-id": "com.reddit.frontpage.alpha:id/top_nav_sale_pill", 
            "scrollable": false, 
            "selected": false, 
            "tag_name": "android.widget.TextView", 
            "text": "FREE", 
            "width": 88, 
            "x": 970, 
            "y": 172
        }, 
        {
            "bounds": "[0,237][1080,2093]", 
            "checkable": false, 
            "checked": false, 
            "class": "android.view.ViewGroup", 
            "clickable": false, 
            "enabled": true, 
            "focusable": false, 
            "focused": false, 
            "hash": "HdOmnDPyIaity79Wosek/g==\n", 
            "height": 1856, 
            "hier_level": 13, 
            "human_hash": "android.view.ViewGroup_X0_Y237_W1080_H1856", 
            "index": "1", 
            "is_transformed": true, 
            "long-clickable": false, 
            "password": false, 
            "resource-id": "com.reddit.frontpage.alpha:id/home_screen", 
            "scrollable": false, 
            "selected": false, 
            "tag_name": "android.view.ViewGroup", 
            "text": "netflix.com/deathto2020 Watch Now Vote 0 Share r/LssAutomation Posted by u/lss_bvt_ios_08   5h LssTest-TextPost-47038 1 Comment Mod Top broadcast Live 4,762 watching Naptime for Valentine LssLiveChat-TextPost LssLiveChat-TextPost", 
            "width": 1080, 
            "x": 0, 
            "y": 237
        }, 
        {
            "bounds": "[0,237][1080,2093]", 
            "checkable": false, 
            "checked": false, 
            "class": "androidx.viewpager.widget.ViewPager", 
            "clickable": false, 
            "enabled": true, 
            "focusable": true, 
            "focused": false, 
            "hash": "4Yr5/wPJpL2UQ11bBQi4QQ==\n", 
            "height": 1856, 
            "hier_level": 14, 
            "human_hash": "androidx.viewpager.widget.ViewPager_X0_Y237_W1080_H1856", 
            "index": "1", 
            "is_transformed": true, 
            "long-clickable": false, 
            "password": false, 
            "resource-id": "com.reddit.frontpage.alpha:id/screen_pager", 
            "scrollable": true, 
            "selected": false, 
            "tag_name": "androidx.viewpager.widget.ViewPager", 
            "text": "netflix.com/deathto2020 Watch Now Vote 0 Share r/LssAutomation Posted by u/lss_bvt_ios_08   5h LssTest-TextPost-47038 1 Comment Mod Top broadcast Live 4,762 watching Naptime for Valentine", 
            "width": 1080, 
            "x": 0, 
            "y": 237
        }, 
        {
            "bounds": "[0,237][1080,2093]", 
            "checkable": false, 
            "checked": false, 
            "class": "android.widget.FrameLayout", 
            "clickable": false, 
            "enabled": true, 
            "focusable": false, 
            "focused": false, 
            "hash": "rZtGRDM2tXipf2mi75EQUQ==\n", 
            "height": 1856, 
            "hier_level": 15, 
            "human_hash": "android.widget.FrameLayout_X0_Y237_W1080_H1856", 
            "index": "0", 
            "is_transformed": true, 
            "long-clickable": false, 
            "password": false, 
            "resource-id": "com.reddit.frontpage.alpha:id/listing_container", 
            "scrollable": false, 
            "selected": false, 
            "tag_name": "android.widget.FrameLayout", 
            "text": "netflix.com/deathto2020 Watch Now Vote 0 Share r/LssAutomation Posted by u/lss_bvt_ios_08   5h LssTest-TextPost-47038 1 Comment Mod Top broadcast Live 4,762 watching Naptime for Valentine", 
            "width": 1080, 
            "x": 0, 
            "y": 237
        }, 
        {
            "bounds": "[0,237][1080,2093]", 
            "checkable": false, 
            "checked": false, 
            "class": "android.widget.FrameLayout", 
            "clickable": false, 
            "enabled": true, 
            "focusable": false, 
            "focused": false, 
            "hash": "rZtGRDM2tXipf2mi75EQUQ==\n", 
            "height": 1856, 
            "hier_level": 16, 
            "human_hash": "android.widget.FrameLayout_X0_Y237_W1080_H1856", 
            "index": "0", 
            "is_transformed": true, 
            "long-clickable": false, 
            "password": false, 
            "resource-id": "com.reddit.frontpage.alpha:id/content_container", 
            "scrollable": false, 
            "selected": false, 
            "tag_name": "android.widget.FrameLayout", 
            "text": "netflix.com/deathto2020 Watch Now Vote 0 Share r/LssAutomation Posted by u/lss_bvt_ios_08   5h LssTest-TextPost-47038 1 Comment Mod Top broadcast Live 4,762 watching Naptime for Valentine", 
            "width": 1080, 
            "x": 0, 
            "y": 237
        }, 
        {
            "bounds": "[0,237][1080,2093]", 
            "checkable": false, 
            "checked": false, 
            "class": "android.view.ViewGroup", 
            "clickable": false, 
            "enabled": true, 
            "focusable": false, 
            "focused": false, 
            "hash": "oIKuX1V3hCUfIv6uAJdfUw==\n", 
            "height": 1856, 
            "hier_level": 17, 
            "human_hash": "android.view.ViewGroup_X0_Y237_W1080_H1856", 
            "index": "0", 
            "is_transformed": true, 
            "long-clickable": false, 
            "password": false, 
            "resource-id": "com.reddit.frontpage.alpha:id/refresh_layout", 
            "scrollable": false, 
            "selected": false, 
            "tag_name": "android.view.ViewGroup", 
            "text": "netflix.com/deathto2020 Watch Now Vote 0 Share r/LssAutomation Posted by u/lss_bvt_ios_08   5h LssTest-TextPost-47038 1 Comment Mod Top broadcast Live 4,762 watching Naptime for Valentine", 
            "width": 1080, 
            "x": 0, 
            "y": 237
        }, 
        {
            "bounds": "[0,237][1080,2093]", 
            "checkable": false, 
            "checked": false, 
            "class": "androidx.recyclerview.widget.RecyclerView", 
            "clickable": false, 
            "enabled": true, 
            "focusable": true, 
            "focused": false, 
            "hash": "XVymKS9sDQBcwaxhP5Tsrg==\n", 
            "height": 1856, 
            "hier_level": 18, 
            "human_hash": "androidx.recyclerview.widget.RecyclerView_X0_Y237_W1080_H1856", 
            "index": "0", 
            "is_transformed": true, 
            "long-clickable": false, 
            "password": false, 
            "resource-id": "com.reddit.frontpage.alpha:id/link_list", 
            "scrollable": true, 
            "selected": false, 
            "tag_name": "androidx.recyclerview.widget.RecyclerView", 
            "text": "netflix.com/deathto2020 Watch Now Vote 0 Share r/LssAutomation Posted by u/lss_bvt_ios_08   5h LssTest-TextPost-47038 1 Comment Mod Top broadcast Live 4,762 watching Naptime for Valentine", 
            "width": 1080, 
            "x": 0, 
            "y": 237
        }, 
        {
            "bounds": "[0,237][1080,710]", 
            "checkable": false, 
            "checked": false, 
            "class": "android.widget.LinearLayout", 
            "clickable": true, 
            "enabled": true, 
            "focusable": true, 
            "focused": false, 
            "hash": "bg9F8lcpv9iQShs3LkQobQ==\n", 
            "height": 473, 
            "hier_level": 19, 
            "human_hash": "android.widget.LinearLayout_X0_Y237_W1080_H473", 
            "index": "0", 
            "is_transformed": true, 
            "long-clickable": false, 
            "password": false, 
            "scrollable": false, 
            "selected": false, 
            "tag_name": "android.widget.LinearLayout", 
            "text": "netflix.com/deathto2020 Watch Now Vote 0 Share", 
            "width": 1080, 
            "x": 0, 
            "y": 237
        }, 
        {
            "bounds": "[0,237][1080,482]", 
            "checkable": false, 
            "checked": false, 
            "class": "android.widget.FrameLayout", 
            "clickable": false, 
            "enabled": true, 
            "focusable": false, 
            "focused": false, 
            "hash": "NHw62ujrIvAdWMXkmIRB+w==\n", 
            "height": 245, 
            "hier_level": 20, 
            "human_hash": "android.widget.FrameLayout_X0_Y237_W1080_H245", 
            "index": "6", 
            "is_transformed": true, 
            "long-clickable": false, 
            "password": false, 
            "scrollable": false, 
            "selected": false, 
            "tag_name": "android.widget.FrameLayout", 
            "text": "", 
            "width": 1080, 
            "x": 0, 
            "y": 237
        }, 
        {
            "bounds": "[0,237][1080,482]", 
            "checkable": false, 
            "checked": false, 
            "class": "android.widget.FrameLayout", 
            "clickable": true, 
            "enabled": true, 
            "focusable": true, 
            "focused": false, 
            "hash": "NHw62ujrIvAdWMXkmIRB+w==\n", 
            "height": 245, 
            "hier_level": 21, 
            "human_hash": "android.widget.FrameLayout_X0_Y237_W1080_H245", 
            "index": "0", 
            "is_transformed": true, 
            "long-clickable": false, 
            "password": false, 
            "resource-id": "com.reddit.frontpage.alpha:id/video_container", 
            "scrollable": false, 
            "selected": false, 
            "tag_name": "android.widget.FrameLayout", 
            "text": "", 
            "width": 1080, 
            "x": 0, 
            "y": 237
        }, 
        {
            "bounds": "[0,237][1080,482]", 
            "checkable": false, 
            "checked": false, 
            "class": "android.widget.FrameLayout", 
            "clickable": true, 
            "enabled": true, 
            "focusable": true, 
            "focused": false, 
            "hash": "NHw62ujrIvAdWMXkmIRB+w==\n", 
            "height": 245, 
            "hier_level": 22, 
            "human_hash": "android.widget.FrameLayout_X0_Y237_W1080_H245", 
            "index": "0", 
            "is_transformed": true, 
            "long-clickable": false, 
            "password": false, 
            "resource-id": "com.reddit.frontpage.alpha:id/video_player", 
            "scrollable": false, 
            "selected": false, 
            "tag_name": "android.widget.FrameLayout", 
            "text": "", 
            "width": 1080, 
            "x": 0, 
            "y": 237
        }, 
        {
            "bounds": "[0,237][1080,482]", 
            "checkable": false, 
            "checked": false, 
            "class": "android.widget.FrameLayout", 
            "clickable": false, 
            "enabled": true, 
            "focusable": false, 
            "focused": false, 
            "hash": "NHw62ujrIvAdWMXkmIRB+w==\n", 
            "height": 245, 
            "hier_level": 23, 
            "human_hash": "android.widget.FrameLayout_X0_Y237_W1080_H245", 
            "index": "0", 
            "is_transformed": true, 
            "long-clickable": false, 
            "password": false, 
            "resource-id": "com.reddit.frontpage.alpha:id/exo_content_frame", 
            "scrollable": false, 
            "selected": false, 
            "tag_name": "android.widget.FrameLayout", 
            "text": "", 
            "width": 1080, 
            "x": 0, 
            "y": 237
        }, 
        {
            "bounds": "[0,237][1080,482]", 
            "checkable": false, 
            "checked": false, 
            "class": "android.view.View", 
            "clickable": false, 
            "enabled": true, 
            "focusable": false, 
            "focused": false, 
            "hash": "uLZCcoWq0DCt1nVASvfNHg==\n", 
            "height": 245, 
            "hier_level": 24, 
            "human_hash": "android.view.View_X0_Y237_W1080_H245", 
            "index": "0", 
            "is_transformed": true, 
            "long-clickable": false, 
            "password": false, 
            "scrollable": false, 
            "selected": false, 
            "tag_name": "android.view.View", 
            "text": "", 
            "width": 1080, 
            "x": 0, 
            "y": 237
        }, 
        {
            "bounds": "[0,383][1080,482]", 
            "checkable": false, 
            "checked": false, 
            "class": "android.widget.FrameLayout", 
            "clickable": false, 
            "enabled": true, 
            "focusable": false, 
            "focused": false, 
            "hash": "KNqXAvLBfJcWObMD4QYTZA==\n", 
            "height": 99, 
            "hier_level": 23, 
            "human_hash": "android.widget.FrameLayout_X0_Y383_W1080_H99", 
            "index": "1", 
            "is_transformed": true, 
            "long-clickable": false, 
            "password": false, 
            "resource-id": "com.reddit.frontpage.alpha:id/exo_progress_view", 
            "scrollable": false, 
            "selected": false, 
            "tag_name": "android.widget.FrameLayout", 
            "text": "", 
            "width": 1080, 
            "x": 0, 
            "y": 383
        }, 
        {
            "bounds": "[0,383][1080,482]", 
            "checkable": false, 
            "checked": false, 
            "class": "android.widget.FrameLayout", 
            "clickable": false, 
            "enabled": true, 
            "focusable": false, 
            "focused": false, 
            "hash": "KNqXAvLBfJcWObMD4QYTZA==\n", 
            "height": 99, 
            "hier_level": 24, 
            "human_hash": "android.widget.FrameLayout_X0_Y383_W1080_H99", 
            "index": "0", 
            "is_transformed": true, 
            "long-clickable": false, 
            "password": false, 
            "scrollable": false, 
            "selected": false, 
            "tag_name": "android.widget.FrameLayout", 
            "text": "", 
            "width": 1080, 
            "x": 0, 
            "y": 383
        }, 
        {
            "bounds": "[0,394][110,482]", 
            "checkable": false, 
            "checked": false, 
            "class": "android.widget.ImageButton", 
            "clickable": true, 
            "enabled": true, 
            "focusable": true, 
            "focused": false, 
            "hash": "pTYoES8c6ra1zcrtaD4D/g==\n", 
            "height": 88, 
            "hier_level": 25, 
            "human_hash": "android.widget.ImageButton_X0_Y394_W110_H88", 
            "index": "0", 
            "is_transformed": true, 
            "long-clickable": false, 
            "password": false, 
            "resource-id": "com.reddit.frontpage.alpha:id/exo_mute_button", 
            "scrollable": false, 
            "selected": false, 
            "tag_name": "android.widget.ImageButton", 
            "text": "", 
            "width": 110, 
            "x": 0, 
            "y": 394
        }, 
        {
            "bounds": "[0,482][1080,600]", 
            "checkable": false, 
            "checked": false, 
            "class": "android.view.ViewGroup", 
            "clickable": true, 
            "enabled": true, 
            "focusable": true, 
            "focused": false, 
            "hash": "SIh1NlSEb+heSMDqwiSXOQ==\n", 
            "height": 118, 
            "hier_level": 20, 
            "human_hash": "android.view.ViewGroup_X0_Y482_W1080_H118", 
            "index": "7", 
            "is_transformed": true, 
            "long-clickable": false, 
            "password": false, 
            "resource-id": "com.reddit.frontpage.alpha:id/promoted_post_cta_view", 
            "scrollable": false, 
            "selected": false, 
            "tag_name": "android.view.ViewGroup", 
            "text": "netflix.com/deathto2020 Watch Now", 
            "width": 1080, 
            "x": 0, 
            "y": 482
        }, 
        {
            "bounds": "[44,519][662,563]", 
            "checkable": false, 
            "checked": false, 
            "class": "android.widget.TextView", 
            "clickable": false, 
            "enabled": true, 
            "focusable": false, 
            "focused": false, 
            "hash": "Dtg8CLjUhDcdYKt5BO5Q4g==\n", 
            "height": 44, 
            "hier_level": 21, 
            "human_hash": "android.widget.TextView_X44_Y519_W618_H44", 
            "index": "0", 
            "is_transformed": true, 
            "long-clickable": false, 
            "password": false, 
            "resource-id": "com.reddit.frontpage.alpha:id/cta_link", 
            "scrollable": false, 
            "selected": false, 
            "tag_name": "android.widget.TextView", 
            "text": "netflix.com/deathto2020", 
            "width": 618, 
            "x": 44, 
            "y": 519
        }, 
        {
            "bounds": "[706,504][1036,578]", 
            "checkable": false, 
            "checked": false, 
            "class": "android.widget.Button", 
            "clickable": true, 
            "enabled": true, 
            "focusable": true, 
            "focused": false, 
            "hash": "gUWVkiCuqrYmmmkd1ZmMNw==\n", 
            "height": 74, 
            "hier_level": 21, 
            "human_hash": "android.widget.Button_X706_Y504_W330_H74", 
            "index": "1", 
            "is_transformed": true, 
            "long-clickable": false, 
            "password": false, 
            "resource-id": "com.reddit.frontpage.alpha:id/cta_button", 
            "scrollable": false, 
            "selected": false, 
            "tag_name": "android.widget.Button", 
            "text": "Watch Now", 
            "width": 330, 
            "x": 706, 
            "y": 504
        }, 
        {
            "bounds": "[0,600][1080,710]", 
            "checkable": false, 
            "checked": false, 
            "class": "android.widget.LinearLayout", 
            "clickable": false, 
            "enabled": true, 
            "focusable": false, 
            "focused": false, 
            "hash": "Wq7rRz4BWQPng9ThPN8bug==\n", 
            "height": 110, 
            "hier_level": 20, 
            "human_hash": "android.widget.LinearLayout_X0_Y600_W1080_H110", 
            "index": "8", 
            "is_transformed": true, 
            "long-clickable": false, 
            "password": false, 
            "resource-id": "com.reddit.frontpage.alpha:id/link_footer", 
            "scrollable": false, 
            "selected": false, 
            "tag_name": "android.widget.LinearLayout", 
            "text": "Vote 0 Share", 
            "width": 1080, 
            "x": 0, 
            "y": 600
        }, 
        {
            "bounds": "[0,600][1080,710]", 
            "checkable": false, 
            "checked": false, 
            "class": "android.view.ViewGroup", 
            "clickable": false, 
            "enabled": true, 
            "focusable": false, 
            "focused": false, 
            "hash": "tcQpcZeAPWsU1u+p5QXbog==\n", 
            "height": 110, 
            "hier_level": 21, 
            "human_hash": "android.view.ViewGroup_X0_Y600_W1080_H110", 
            "index": "0", 
            "is_transformed": true, 
            "long-clickable": false, 
            "password": false, 
            "scrollable": false, 
            "selected": false, 
            "tag_name": "android.view.ViewGroup", 
            "text": "Vote 0 Share", 
            "width": 1080, 
            "x": 0, 
            "y": 600
        }, 
        {
            "bounds": "[0,600][300,710]", 
            "checkable": false, 
            "checked": false, 
            "class": "android.widget.LinearLayout", 
            "clickable": true, 
            "enabled": true, 
            "focusable": true, 
            "focused": false, 
            "hash": "7R/7N7obPZ5HMN3awuPp3w==\n", 
            "height": 110, 
            "hier_level": 22, 
            "human_hash": "android.widget.LinearLayout_X0_Y600_W300_H110", 
            "index": "1", 
            "is_transformed": true, 
            "long-clickable": false, 
            "password": false, 
            "resource-id": "com.reddit.frontpage.alpha:id/vote", 
            "scrollable": false, 
            "selected": false, 
            "tag_name": "android.widget.LinearLayout", 
            "text": "Vote", 
            "width": 300, 
            "x": 0, 
            "y": 600
        }, 
        {
            "bounds": "[44,633][88,677]", 
            "checkable": false, 
            "checked": false, 
            "class": "android.widget.ImageView", 
            "clickable": true, 
            "content-desc": "Upvote", 
            "enabled": true, 
            "focusable": true, 
            "focused": false, 
            "hash": "LSVnX98hink10/EJ05MkyQ==\n", 
            "height": 44, 
            "hier_level": 23, 
            "human_hash": "android.widget.ImageView_X44_Y633_W44_H44", 
            "index": "0", 
            "is_transformed": true, 
            "long-clickable": false, 
            "password": false, 
            "resource-id": "com.reddit.frontpage.alpha:id/vote_view_upvote", 
            "scrollable": false, 
            "selected": false, 
            "tag_name": "android.widget.ImageView", 
            "text": "", 
            "width": 44, 
            "x": 44, 
            "y": 633
        }, 
        {
            "bounds": "[110,628][190,681]", 
            "checkable": false, 
            "checked": false, 
            "class": "android.widget.TextView", 
            "clickable": false, 
            "enabled": true, 
            "focusable": false, 
            "focused": false, 
            "hash": "m7efQo7lL44myduL4IJ0OQ==\n", 
            "height": 53, 
            "hier_level": 23, 
            "human_hash": "android.widget.TextView_X110_Y628_W80_H53", 
            "index": "1", 
            "is_transformed": true, 
            "long-clickable": false, 
            "password": false, 
            "resource-id": "com.reddit.frontpage.alpha:id/vote_view_score", 
            "scrollable": false, 
            "selected": false, 
            "tag_name": "android.widget.TextView", 
            "text": "Vote", 
            "width": 80, 
            "x": 110, 
            "y": 628
        }, 
        {
            "bounds": "[212,633][256,677]", 
            "checkable": false, 
            "checked": false, 
            "class": "android.widget.ImageView", 
            "clickable": true, 
            "content-desc": "Downvote", 
            "enabled": true, 
            "focusable": true, 
            "focused": false, 
            "hash": "9AJdm1w83t5PGF91ECGlOA==\n", 
            "height": 44, 
            "hier_level": 23, 
            "human_hash": "android.widget.ImageView_X212_Y633_W44_H44", 
            "index": "2", 
            "is_transformed": true, 
            "long-clickable": false, 
            "password": false, 
            "resource-id": "com.reddit.frontpage.alpha:id/vote_view_downvote", 
            "scrollable": false, 
            "selected": false, 
            "tag_name": "android.widget.ImageView", 
            "text": "", 
            "width": 44, 
            "x": 212, 
            "y": 633
        }, 
        {
            "bounds": "[442,600][530,710]", 
            "checkable": false, 
            "checked": false, 
            "class": "android.widget.TextView", 
            "clickable": true, 
            "enabled": true, 
            "focusable": true, 
            "focused": false, 
            "hash": "442aBCgGPKSskvabIKgWxg==\n", 
            "height": 110, 
            "hier_level": 22, 
            "human_hash": "android.widget.TextView_X442_Y600_W88_H110", 
            "index": "2", 
            "is_transformed": true, 
            "long-clickable": false, 
            "password": false, 
            "resource-id": "com.reddit.frontpage.alpha:id/comments", 
            "scrollable": false, 
            "selected": false, 
            "tag_name": "android.widget.TextView", 
            "text": "0", 
            "width": 88, 
            "x": 442, 
            "y": 600
        }, 
        {
            "bounds": "[714,600][882,710]", 
            "checkable": false, 
            "checked": false, 
            "class": "android.widget.TextView", 
            "clickable": true, 
            "enabled": true, 
            "focusable": true, 
            "focused": false, 
            "hash": "UapT8VPgu3ho5EMPCb46zQ==\n", 
            "height": 110, 
            "hier_level": 22, 
            "human_hash": "android.widget.TextView_X714_Y600_W168_H110", 
            "index": "3", 
            "is_transformed": true, 
            "long-clickable": false, 
            "password": false, 
            "resource-id": "com.reddit.frontpage.alpha:id/extra_action", 
            "scrollable": false, 
            "selected": false, 
            "tag_name": "android.widget.TextView", 
            "text": "Share", 
            "width": 168, 
            "x": 714, 
            "y": 600
        }, 
        {
            "bounds": "[970,600][1058,710]", 
            "checkable": false, 
            "checked": false, 
            "class": "android.widget.ImageView", 
            "clickable": true, 
            "content-desc": "Give Award", 
            "enabled": true, 
            "focusable": true, 
            "focused": false, 
            "hash": "qz2TKvRj3U4kK1J6fpsYaw==\n", 
            "height": 110, 
            "hier_level": 22, 
            "human_hash": "android.widget.ImageView_X970_Y600_W88_H110", 
            "index": "4", 
            "is_transformed": true, 
            "long-clickable": false, 
            "password": false, 
            "resource-id": "com.reddit.frontpage.alpha:id/award_cta_icon", 
            "scrollable": false, 
            "selected": false, 
            "tag_name": "android.widget.ImageView", 
            "text": "", 
            "width": 88, 
            "x": 970, 
            "y": 600
        }, 
        {
            "bounds": "[0,732][1080,1041]", 
            "checkable": false, 
            "checked": false, 
            "class": "android.widget.LinearLayout", 
            "clickable": true, 
            "enabled": true, 
            "focusable": true, 
            "focused": false, 
            "hash": "owsqd2NaQ25miBvteNVxaA==\n", 
            "height": 309, 
            "hier_level": 19, 
            "human_hash": "android.widget.LinearLayout_X0_Y732_W1080_H309", 
            "index": "1", 
            "is_transformed": true, 
            "long-clickable": false, 
            "password": false, 
            "scrollable": false, 
            "selected": false, 
            "tag_name": "android.widget.LinearLayout", 
            "text": "r/LssAutomation Posted by u/lss_bvt_ios_08   5h LssTest-TextPost-47038 1 Comment Mod", 
            "width": 1080, 
            "x": 0, 
            "y": 732
        }, 
        {
            "bounds": "[0,732][1080,864]", 
            "checkable": false, 
            "checked": false, 
            "class": "android.view.ViewGroup", 
            "clickable": false, 
            "enabled": true, 
            "focusable": false, 
            "focused": false, 
            "hash": "d4Kk3BvRQ7Ogzdg0aF6/Cg==\n", 
            "height": 132, 
            "hier_level": 20, 
            "human_hash": "android.view.ViewGroup_X0_Y732_W1080_H132", 
            "index": "0", 
            "is_transformed": true, 
            "long-clickable": false, 
            "password": false, 
            "resource-id": "com.reddit.frontpage.alpha:id/subscribe_header", 
            "scrollable": false, 
            "selected": false, 
            "tag_name": "android.view.ViewGroup", 
            "text": "r/LssAutomation Posted by u/lss_bvt_ios_08   5h", 
            "width": 1080, 
            "x": 0, 
            "y": 732
        }, 
        {
            "bounds": "[44,754][132,842]", 
            "checkable": false, 
            "checked": false, 
            "class": "android.widget.FrameLayout", 
            "clickable": true, 
            "content-desc": "Avatar", 
            "enabled": true, 
            "focusable": true, 
            "focused": false, 
            "hash": "W7TaGf2h53hxl085GWuT9w==\n", 
            "height": 88, 
            "hier_level": 21, 
            "human_hash": "android.widget.FrameLayout_X44_Y754_W88_H88", 
            "index": "1", 
            "is_transformed": true, 
            "long-clickable": false, 
            "password": false, 
            "resource-id": "com.reddit.frontpage.alpha:id/detail_subreddit_icon", 
            "scrollable": false, 
            "selected": false, 
            "tag_name": "android.widget.FrameLayout", 
            "text": "", 
            "width": 88, 
            "x": 44, 
            "y": 754
        }, 
        {
            "bounds": "[44,754][132,842]", 
            "checkable": false, 
            "checked": false, 
            "class": "android.widget.ImageView", 
            "clickable": false, 
            "enabled": true, 
            "focusable": false, 
            "focused": false, 
            "hash": "56A3JdfW3Mkur5ukvB9dmg==\n", 
            "height": 88, 
            "hier_level": 22, 
            "human_hash": "android.widget.ImageView_X44_Y754_W88_H88", 
            "index": "0", 
            "is_transformed": true, 
            "long-clickable": false, 
            "password": false, 
            "resource-id": "com.reddit.frontpage.alpha:id/inner_avatar", 
            "scrollable": false, 
            "selected": false, 
            "tag_name": "android.widget.ImageView", 
            "text": "", 
            "width": 88, 
            "x": 44, 
            "y": 754
        }, 
        {
            "bounds": "[132,751][459,804]", 
            "checkable": false, 
            "checked": false, 
            "class": "android.widget.TextView", 
            "clickable": true, 
            "enabled": true, 
            "focusable": true, 
            "focused": false, 
            "hash": "IBubt3trg0K/vHUghFyVUw==\n", 
            "height": 53, 
            "hier_level": 21, 
            "human_hash": "android.widget.TextView_X132_Y751_W327_H53", 
            "index": "2", 
            "is_transformed": true, 
            "long-clickable": false, 
            "password": false, 
            "resource-id": "com.reddit.frontpage.alpha:id/detail_subreddit_name", 
            "scrollable": false, 
            "selected": false, 
            "tag_name": "android.widget.TextView", 
            "text": "r/LssAutomation", 
            "width": 327, 
            "x": 132, 
            "y": 751
        }, 
        {
            "bounds": "[154,803][1003,847]", 
            "checkable": false, 
            "checked": false, 
            "class": "android.widget.FrameLayout", 
            "clickable": false, 
            "enabled": true, 
            "focusable": false, 
            "focused": false, 
            "hash": "91g0qdF+0ktABrgnVfdSLw==\n", 
            "height": 44, 
            "hier_level": 21, 
            "human_hash": "android.widget.FrameLayout_X154_Y803_W849_H44", 
            "index": "3", 
            "is_transformed": true, 
            "long-clickable": false, 
            "password": false, 
            "resource-id": "com.reddit.frontpage.alpha:id/metadata_container", 
            "scrollable": false, 
            "selected": false, 
            "tag_name": "android.widget.FrameLayout", 
            "text": "Posted by u/lss_bvt_ios_08   5h", 
            "width": 849, 
            "x": 154, 
            "y": 803
        }, 
        {
            "bounds": "[154,803][1003,847]", 
            "checkable": false, 
            "checked": false, 
            "class": "android.widget.LinearLayout", 
            "clickable": false, 
            "enabled": true, 
            "focusable": false, 
            "focused": false, 
            "hash": "e4+mKxdgwLKUbY3hB6Yncw==\n", 
            "height": 44, 
            "hier_level": 22, 
            "human_hash": "android.widget.LinearLayout_X154_Y803_W849_H44", 
            "index": "0", 
            "is_transformed": true, 
            "long-clickable": false, 
            "password": false, 
            "scrollable": false, 
            "selected": false, 
            "tag_name": "android.widget.LinearLayout", 
            "text": "Posted by u/lss_bvt_ios_08   5h", 
            "width": 849, 
            "x": 154, 
            "y": 803
        }, 
        {
            "bounds": "[154,803][556,847]", 
            "checkable": false, 
            "checked": false, 
            "class": "android.widget.TextView", 
            "clickable": true, 
            "enabled": true, 
            "focusable": true, 
            "focused": false, 
            "hash": "QVT+iM5/xrBlPynyTZIrAQ==\n", 
            "height": 44, 
            "hier_level": 23, 
            "human_hash": "android.widget.TextView_X154_Y803_W402_H44", 
            "index": "0", 
            "is_transformed": true, 
            "long-clickable": false, 
            "password": false, 
            "resource-id": "com.reddit.frontpage.alpha:id/bottom_row_metadata_before_indicators", 
            "scrollable": false, 
            "selected": false, 
            "tag_name": "android.widget.TextView", 
            "text": "Posted by u/lss_bvt_ios_08", 
            "width": 402, 
            "x": 154, 
            "y": 803
        }, 
        {
            "bounds": "[556,803][620,847]", 
            "checkable": false, 
            "checked": false, 
            "class": "android.widget.TextView", 
            "clickable": false, 
            "enabled": true, 
            "focusable": false, 
            "focused": false, 
            "hash": "5O1EVxNyUCPOBL3HviCv6g==\n", 
            "height": 44, 
            "hier_level": 23, 
            "human_hash": "android.widget.TextView_X556_Y803_W64_H44", 
            "index": "1", 
            "is_transformed": true, 
            "long-clickable": false, 
            "password": false, 
            "resource-id": "com.reddit.frontpage.alpha:id/bottom_row_metadata_after_indicators", 
            "scrollable": false, 
            "selected": false, 
            "tag_name": "android.widget.TextView", 
            "text": "  5h", 
            "width": 64, 
            "x": 556, 
            "y": 803
        }, 
        {
            "bounds": "[997,754][1074,831]", 
            "checkable": false, 
            "checked": false, 
            "class": "android.widget.ImageView", 
            "clickable": true, 
            "enabled": true, 
            "focusable": true, 
            "focused": false, 
            "hash": "GFQU3EQZYdIRx86ppUZH7A==\n", 
            "height": 77, 
            "hier_level": 21, 
            "human_hash": "android.widget.ImageView_X997_Y754_W77_H77", 
            "index": "4", 
            "is_transformed": true, 
            "long-clickable": false, 
            "password": false, 
            "resource-id": "com.reddit.frontpage.alpha:id/overflow", 
            "scrollable": false, 
            "selected": false, 
            "tag_name": "android.widget.ImageView", 
            "text": "", 
            "width": 77, 
            "x": 997, 
            "y": 754
        }, 
        {
            "bounds": "[0,864][1080,931]", 
            "checkable": false, 
            "checked": false, 
            "class": "android.widget.RelativeLayout", 
            "clickable": false, 
            "enabled": true, 
            "focusable": false, 
            "focused": false, 
            "hash": "gBGUhJ5i/hlkOJ9t8DMrew==\n", 
            "height": 67, 
            "hier_level": 20, 
            "human_hash": "android.widget.RelativeLayout_X0_Y864_W1080_H67", 
            "index": "1", 
            "is_transformed": true, 
            "long-clickable": false, 
            "password": false, 
            "resource-id": "com.reddit.frontpage.alpha:id/link_card_body", 
            "scrollable": false, 
            "selected": false, 
            "tag_name": "android.widget.RelativeLayout", 
            "text": "LssTest-TextPost-47038", 
            "width": 1080, 
            "x": 0, 
            "y": 864
        }, 
        {
            "bounds": "[44,864][1036,931]", 
            "checkable": false, 
            "checked": false, 
            "class": "android.widget.TextView", 
            "clickable": false, 
            "enabled": true, 
            "focusable": false, 
            "focused": false, 
            "hash": "BZZScvE5mSSO8rdc35ls/g==\n", 
            "height": 67, 
            "hier_level": 21, 
            "human_hash": "android.widget.TextView_X44_Y864_W992_H67", 
            "index": "2", 
            "is_transformed": true, 
            "long-clickable": false, 
            "password": false, 
            "resource-id": "com.reddit.frontpage.alpha:id/link_title", 
            "scrollable": false, 
            "selected": false, 
            "tag_name": "android.widget.TextView", 
            "text": "LssTest-TextPost-47038", 
            "width": 992, 
            "x": 44, 
            "y": 864
        }, 
        {
            "bounds": "[0,931][1080,1041]", 
            "checkable": false, 
            "checked": false, 
            "class": "android.widget.LinearLayout", 
            "clickable": false, 
            "enabled": true, 
            "focusable": false, 
            "focused": false, 
            "hash": "R4VFpK7UTI/KpPCJPXyghA==\n", 
            "height": 110, 
            "hier_level": 20, 
            "human_hash": "android.widget.LinearLayout_X0_Y931_W1080_H110", 
            "index": "2", 
            "is_transformed": true, 
            "long-clickable": false, 
            "password": false, 
            "resource-id": "com.reddit.frontpage.alpha:id/link_footer", 
            "scrollable": false, 
            "selected": false, 
            "tag_name": "android.widget.LinearLayout", 
            "text": "1 Comment Mod", 
            "width": 1080, 
            "x": 0, 
            "y": 931
        }, 
        {
            "bounds": "[0,931][1080,1041]", 
            "checkable": false, 
            "checked": false, 
            "class": "android.view.ViewGroup", 
            "clickable": false, 
            "enabled": true, 
            "focusable": false, 
            "focused": false, 
            "hash": "URexUh22zMkNLO/dX4BAhQ==\n", 
            "height": 110, 
            "hier_level": 21, 
            "human_hash": "android.view.ViewGroup_X0_Y931_W1080_H110", 
            "index": "0", 
            "is_transformed": true, 
            "long-clickable": false, 
            "password": false, 
            "scrollable": false, 
            "selected": false, 
            "tag_name": "android.view.ViewGroup", 
            "text": "1 Comment Mod", 
            "width": 1080, 
            "x": 0, 
            "y": 931
        }, 
        {
            "bounds": "[0,931][242,1041]", 
            "checkable": false, 
            "checked": false, 
            "class": "android.widget.LinearLayout", 
            "clickable": true, 
            "enabled": true, 
            "focusable": true, 
            "focused": false, 
            "hash": "UXId12MzdKDkuYkwlNs3EQ==\n", 
            "height": 110, 
            "hier_level": 22, 
            "human_hash": "android.widget.LinearLayout_X0_Y931_W242_H110", 
            "index": "1", 
            "is_transformed": true, 
            "long-clickable": false, 
            "password": false, 
            "resource-id": "com.reddit.frontpage.alpha:id/vote", 
            "scrollable": false, 
            "selected": false, 
            "tag_name": "android.widget.LinearLayout", 
            "text": "1", 
            "width": 242, 
            "x": 0, 
            "y": 931
        }, 
        {
            "bounds": "[44,964][88,1008]", 
            "checkable": false, 
            "checked": false, 
            "class": "android.widget.ImageView", 
            "clickable": true, 
            "content-desc": "Upvote", 
            "enabled": true, 
            "focusable": true, 
            "focused": false, 
            "hash": "v2KN9bz/FvGHYPQyFsRXYA==\n", 
            "height": 44, 
            "hier_level": 23, 
            "human_hash": "android.widget.ImageView_X44_Y964_W44_H44", 
            "index": "0", 
            "is_transformed": true, 
            "long-clickable": false, 
            "password": false, 
            "resource-id": "com.reddit.frontpage.alpha:id/vote_view_upvote", 
            "scrollable": false, 
            "selected": false, 
            "tag_name": "android.widget.ImageView", 
            "text": "", 
            "width": 44, 
            "x": 44, 
            "y": 964
        }, 
        {
            "bounds": "[110,959][132,1012]", 
            "checkable": false, 
            "checked": false, 
            "class": "android.widget.TextView", 
            "clickable": false, 
            "enabled": true, 
            "focusable": false, 
            "focused": false, 
            "hash": "Sr3prz0CdclEntDMgREqKQ==\n", 
            "height": 53, 
            "hier_level": 23, 
            "human_hash": "android.widget.TextView_X110_Y959_W22_H53", 
            "index": "1", 
            "is_transformed": true, 
            "long-clickable": false, 
            "password": false, 
            "resource-id": "com.reddit.frontpage.alpha:id/vote_view_score", 
            "scrollable": false, 
            "selected": false, 
            "tag_name": "android.widget.TextView", 
            "text": "1", 
            "width": 22, 
            "x": 110, 
            "y": 959
        }, 
        {
            "bounds": "[154,964][198,1008]", 
            "checkable": false, 
            "checked": false, 
            "class": "android.widget.ImageView", 
            "clickable": true, 
            "content-desc": "Downvote", 
            "enabled": true, 
            "focusable": true, 
            "focused": false, 
            "hash": "JXL/2zzMRgDfjGE8TsGT5g==\n", 
            "height": 44, 
            "hier_level": 23, 
            "human_hash": "android.widget.ImageView_X154_Y964_W44_H44", 
            "index": "2", 
            "is_transformed": true, 
            "long-clickable": false, 
            "password": false, 
            "resource-id": "com.reddit.frontpage.alpha:id/vote_view_downvote", 
            "scrollable": false, 
            "selected": false, 
            "tag_name": "android.widget.ImageView", 
            "text": "", 
            "width": 44, 
            "x": 154, 
            "y": 964
        }, 
        {
            "bounds": "[368,931][605,1041]", 
            "checkable": false, 
            "checked": false, 
            "class": "android.widget.TextView", 
            "clickable": true, 
            "enabled": true, 
            "focusable": true, 
            "focused": false, 
            "hash": "yurerndUBjRC8g8XqvoWoA==\n", 
            "height": 110, 
            "hier_level": 22, 
            "human_hash": "android.widget.TextView_X368_Y931_W237_H110", 
            "index": "2", 
            "is_transformed": true, 
            "long-clickable": false, 
            "password": false, 
            "resource-id": "com.reddit.frontpage.alpha:id/comments", 
            "scrollable": false, 
            "selected": false, 
            "tag_name": "android.widget.TextView", 
            "text": "Comment", 
            "width": 237, 
            "x": 368, 
            "y": 931
        }, 
        {
            "bounds": "[726,931][870,1041]", 
            "checkable": false, 
            "checked": false, 
            "class": "android.widget.TextView", 
            "clickable": true, 
            "enabled": true, 
            "focusable": true, 
            "focused": false, 
            "hash": "BBL+bW4DuNnV2brlzVPaOg==\n", 
            "height": 110, 
            "hier_level": 22, 
            "human_hash": "android.widget.TextView_X726_Y931_W144_H110", 
            "index": "3", 
            "is_transformed": true, 
            "long-clickable": false, 
            "password": false, 
            "resource-id": "com.reddit.frontpage.alpha:id/extra_action", 
            "scrollable": false, 
            "selected": false, 
            "tag_name": "android.widget.TextView", 
            "text": "Mod", 
            "width": 144, 
            "x": 726, 
            "y": 931
        }, 
        {
            "bounds": "[970,931][1058,1041]", 
            "checkable": false, 
            "checked": false, 
            "class": "android.widget.ImageView", 
            "clickable": true, 
            "content-desc": "Give Award", 
            "enabled": true, 
            "focusable": true, 
            "focused": false, 
            "hash": "M+kC1T8Noa8Pkm/wyas/hg==\n", 
            "height": 110, 
            "hier_level": 22, 
            "human_hash": "android.widget.ImageView_X970_Y931_W88_H110", 
            "index": "4", 
            "is_transformed": true, 
            "long-clickable": false, 
            "password": false, 
            "resource-id": "com.reddit.frontpage.alpha:id/award_cta_icon", 
            "scrollable": false, 
            "selected": false, 
            "tag_name": "android.widget.ImageView", 
            "text": "", 
            "width": 88, 
            "x": 970, 
            "y": 931
        }, 
        {
            "bounds": "[0,1063][1080,2093]", 
            "checkable": false, 
            "checked": false, 
            "class": "android.view.ViewGroup", 
            "clickable": true, 
            "enabled": true, 
            "focusable": true, 
            "focused": false, 
            "hash": "jSHA6j7c2vjty8V9D9zb0g==\n", 
            "height": 1030, 
            "hier_level": 19, 
            "human_hash": "android.view.ViewGroup_X0_Y1063_W1080_H1030", 
            "index": "2", 
            "is_transformed": true, 
            "long-clickable": false, 
            "password": false, 
            "scrollable": false, 
            "selected": false, 
            "tag_name": "android.view.ViewGroup", 
            "text": "Top broadcast Live 4,762 watching Naptime for Valentine", 
            "width": 1080, 
            "x": 0, 
            "y": 1063
        }, 
        {
            "bounds": "[0,1063][1080,1188]", 
            "checkable": false, 
            "checked": false, 
            "class": "android.view.ViewGroup", 
            "clickable": false, 
            "enabled": true, 
            "focusable": false, 
            "focused": false, 
            "hash": "WrR8YExH1tbJylQs7E/HBw==\n", 
            "height": 125, 
            "hier_level": 20, 
            "human_hash": "android.view.ViewGroup_X0_Y1063_W1080_H125", 
            "index": "0", 
            "is_transformed": true, 
            "long-clickable": false, 
            "password": false, 
            "resource-id": "com.reddit.frontpage.alpha:id/info_bar", 
            "scrollable": false, 
            "selected": false, 
            "tag_name": "android.view.ViewGroup", 
            "text": "Top broadcast", 
            "width": 1080, 
            "x": 0, 
            "y": 1063
        }, 
        {
            "bounds": "[33,1096][316,1155]", 
            "checkable": false, 
            "checked": false, 
            "class": "android.widget.TextView", 
            "clickable": false, 
            "enabled": true, 
            "focusable": false, 
            "focused": false, 
            "hash": "BIwgmJD3RswKikFsqBrpWA==\n", 
            "height": 59, 
            "hier_level": 21, 
            "human_hash": "android.widget.TextView_X33_Y1096_W283_H59", 
            "index": "0", 
            "is_transformed": true, 
            "long-clickable": false, 
            "password": false, 
            "resource-id": "com.reddit.frontpage.alpha:id/stream_info", 
            "scrollable": false, 
            "selected": false, 
            "tag_name": "android.widget.TextView", 
            "text": "Top broadcast", 
            "width": 283, 
            "x": 33, 
            "y": 1096
        }, 
        {
            "bounds": "[992,1088][1058,1163]", 
            "checkable": false, 
            "checked": false, 
            "class": "android.widget.ImageView", 
            "clickable": true, 
            "content-desc": "Menu", 
            "enabled": true, 
            "focusable": true, 
            "focused": false, 
            "hash": "ZmEF4a0Q08g7YqeRk99quQ==\n", 
            "height": 75, 
            "hier_level": 21, 
            "human_hash": "android.widget.ImageView_X992_Y1088_W66_H75", 
            "index": "1", 
            "is_transformed": true, 
            "long-clickable": false, 
            "password": false, 
            "resource-id": "com.reddit.frontpage.alpha:id/stream_overflow", 
            "scrollable": false, 
            "selected": false, 
            "tag_name": "android.widget.ImageView", 
            "text": "", 
            "width": 66, 
            "x": 992, 
            "y": 1088
        }, 
        {
            "bounds": "[0,1188][1080,2093]", 
            "checkable": false, 
            "checked": false, 
            "class": "android.widget.FrameLayout", 
            "clickable": false, 
            "enabled": true, 
            "focusable": false, 
            "focused": false, 
            "hash": "4dogHjo0FWugOJDe2hKnVw==\n", 
            "height": 905, 
            "hier_level": 20, 
            "human_hash": "android.widget.FrameLayout_X0_Y1188_W1080_H905", 
            "index": "1", 
            "is_transformed": true, 
            "long-clickable": false, 
            "password": false, 
            "resource-id": "com.reddit.frontpage.alpha:id/video_player", 
            "scrollable": false, 
            "selected": false, 
            "tag_name": "android.widget.FrameLayout", 
            "text": "", 
            "width": 1080, 
            "x": 0, 
            "y": 1188
        }, 
        {
            "bounds": "[0,1188][1080,2093]", 
            "checkable": false, 
            "checked": false, 
            "class": "android.widget.FrameLayout", 
            "clickable": false, 
            "enabled": true, 
            "focusable": false, 
            "focused": false, 
            "hash": "4dogHjo0FWugOJDe2hKnVw==\n", 
            "height": 905, 
            "hier_level": 21, 
            "human_hash": "android.widget.FrameLayout_X0_Y1188_W1080_H905", 
            "index": "0", 
            "is_transformed": true, 
            "long-clickable": false, 
            "password": false, 
            "resource-id": "com.reddit.frontpage.alpha:id/exo_content_frame", 
            "scrollable": false, 
            "selected": false, 
            "tag_name": "android.widget.FrameLayout", 
            "text": "", 
            "width": 1080, 
            "x": 0, 
            "y": 1188
        }, 
        {
            "bounds": "[0,1188][1080,2093]", 
            "checkable": false, 
            "checked": false, 
            "class": "android.view.View", 
            "clickable": false, 
            "enabled": true, 
            "focusable": false, 
            "focused": false, 
            "hash": "xUYikMO0GGHkfuVKFy0tsw==\n", 
            "height": 905, 
            "hier_level": 22, 
            "human_hash": "android.view.View_X0_Y1188_W1080_H905", 
            "index": "0", 
            "is_transformed": true, 
            "long-clickable": false, 
            "password": false, 
            "scrollable": false, 
            "selected": false, 
            "tag_name": "android.view.View", 
            "text": "", 
            "width": 1080, 
            "x": 0, 
            "y": 1188
        }, 
        {
            "bounds": "[430,1618][650,1838]", 
            "checkable": false, 
            "checked": false, 
            "class": "android.widget.ImageView", 
            "clickable": false, 
            "content-desc": "Expand", 
            "enabled": true, 
            "focusable": false, 
            "focused": false, 
            "hash": "YD2xe2FQJkgMJRoZ6NOz6w==\n", 
            "height": 220, 
            "hier_level": 21, 
            "human_hash": "android.widget.ImageView_X430_Y1618_W220_H220", 
            "index": "1", 
            "is_transformed": true, 
            "long-clickable": false, 
            "password": false, 
            "resource-id": "com.reddit.frontpage.alpha:id/stream_expand", 
            "scrollable": false, 
            "selected": false, 
            "tag_name": "android.widget.ImageView", 
            "text": "", 
            "width": 220, 
            "x": 430, 
            "y": 1618
        }, 
        {
            "bounds": "[22,1210][157,1275]", 
            "checkable": false, 
            "checked": false, 
            "class": "android.widget.TextView", 
            "clickable": false, 
            "enabled": true, 
            "focusable": false, 
            "focused": false, 
            "hash": "l62Dcigp7ntObWAxhM3JEw==\n", 
            "height": 65, 
            "hier_level": 20, 
            "human_hash": "android.widget.TextView_X22_Y1210_W135_H65", 
            "index": "2", 
            "is_transformed": true, 
            "long-clickable": false, 
            "password": false, 
            "resource-id": "com.reddit.frontpage.alpha:id/live_indicator_left", 
            "scrollable": false, 
            "selected": false, 
            "tag_name": "android.widget.TextView", 
            "text": "Live", 
            "width": 135, 
            "x": 22, 
            "y": 1210
        }, 
        {
            "bounds": "[179,1216][442,1269]", 
            "checkable": false, 
            "checked": false, 
            "class": "android.widget.TextView", 
            "clickable": false, 
            "enabled": true, 
            "focusable": false, 
            "focused": false, 
            "hash": "JRSZ25G2u0JfnEY3EMH27g==\n", 
            "height": 53, 
            "hier_level": 20, 
            "human_hash": "android.widget.TextView_X179_Y1216_W263_H53", 
            "index": "3", 
            "is_transformed": true, 
            "long-clickable": false, 
            "password": false, 
            "resource-id": "com.reddit.frontpage.alpha:id/feature_stream_watcher_copy", 
            "scrollable": false, 
            "selected": false, 
            "tag_name": "android.widget.TextView", 
            "text": "4,762 watching", 
            "width": 263, 
            "x": 179, 
            "y": 1216
        }, 
        {
            "bounds": "[22,1297][1058,1364]", 
            "checkable": false, 
            "checked": false, 
            "class": "android.widget.TextView", 
            "clickable": false, 
            "enabled": true, 
            "focusable": false, 
            "focused": false, 
            "hash": "NqhK6+pIH/yVUxOdLAI45Q==\n", 
            "height": 67, 
            "hier_level": 20, 
            "human_hash": "android.widget.TextView_X22_Y1297_W1036_H67", 
            "index": "4", 
            "is_transformed": true, 
            "long-clickable": false, 
            "password": false, 
            "resource-id": "com.reddit.frontpage.alpha:id/stream_title", 
            "scrollable": false, 
            "selected": false, 
            "tag_name": "android.widget.TextView", 
            "text": "Naptime for Valentine", 
            "width": 1036, 
            "x": 22, 
            "y": 1297
        }, 
        {
            "bounds": "[893,1855][1058,2093]", 
            "checkable": false, 
            "checked": false, 
            "class": "android.widget.ImageView", 
            "clickable": false, 
            "enabled": true, 
            "focusable": false, 
            "focused": false, 
            "hash": "n+dfIXzomXVxrfXuAzih3g==\n", 
            "height": 238, 
            "hier_level": 20, 
            "human_hash": "android.widget.ImageView_X893_Y1855_W165_H238", 
            "index": "5", 
            "is_transformed": true, 
            "long-clickable": false, 
            "password": false, 
            "resource-id": "com.reddit.frontpage.alpha:id/upvote_animation", 
            "scrollable": false, 
            "selected": false, 
            "tag_name": "android.widget.ImageView", 
            "text": "", 
            "width": 165, 
            "x": 893, 
            "y": 1855
        }, 
        {
            "bounds": "[0,237][1080,248]", 
            "checkable": false, 
            "checked": false, 
            "class": "android.view.View", 
            "clickable": false, 
            "enabled": true, 
            "focusable": false, 
            "focused": false, 
            "hash": "SR9683JUiTTIWwCYKtj1OA==\n", 
            "height": 11, 
            "hier_level": 16, 
            "human_hash": "android.view.View_X0_Y237_W1080_H11", 
            "index": "1", 
            "is_transformed": true, 
            "long-clickable": false, 
            "password": false, 
            "scrollable": false, 
            "selected": false, 
            "tag_name": "android.view.View", 
            "text": "", 
            "width": 1080, 
            "x": 0, 
            "y": 237
        }, 
        {
            "bounds": "[0,1850][1080,2093]", 
            "checkable": false, 
            "checked": false, 
            "class": "android.widget.FrameLayout", 
            "clickable": false, 
            "enabled": true, 
            "focusable": false, 
            "focused": false, 
            "hash": "cRLa1EnZKVICZioVgdeZEw==\n", 
            "height": 243, 
            "hier_level": 14, 
            "human_hash": "android.widget.FrameLayout_X0_Y1850_W1080_H243", 
            "index": "2", 
            "is_transformed": true, 
            "long-clickable": false, 
            "password": false, 
            "resource-id": "com.reddit.frontpage.alpha:id/recent_chat_posts_popup_overlay", 
            "scrollable": false, 
            "selected": false, 
            "tag_name": "android.widget.FrameLayout", 
            "text": "LssLiveChat-TextPost LssLiveChat-TextPost", 
            "width": 1080, 
            "x": 0, 
            "y": 1850
        }, 
        {
            "bounds": "[766,1850][1041,2060]", 
            "checkable": false, 
            "checked": false, 
            "class": "androidx.recyclerview.widget.RecyclerView", 
            "clickable": false, 
            "enabled": true, 
            "focusable": true, 
            "focused": false, 
            "hash": "Lk8KCAux7nRxOmICH3ZroA==\n", 
            "height": 210, 
            "hier_level": 15, 
            "human_hash": "androidx.recyclerview.widget.RecyclerView_X766_Y1850_W275_H210", 
            "index": "0", 
            "is_transformed": true, 
            "long-clickable": false, 
            "password": false, 
            "resource-id": "com.reddit.frontpage.alpha:id/recent_chat_posts", 
            "scrollable": false, 
            "selected": false, 
            "tag_name": "androidx.recyclerview.widget.RecyclerView", 
            "text": "LssLiveChat-TextPost LssLiveChat-TextPost", 
            "width": 275, 
            "x": 766, 
            "y": 1850
        }, 
        {
            "bounds": "[772,1856][1035,1944]", 
            "checkable": false, 
            "checked": false, 
            "class": "android.widget.LinearLayout", 
            "clickable": true, 
            "enabled": true, 
            "focusable": true, 
            "focused": false, 
            "hash": "qB7z83lLS6SzUkkBweHHSQ==\n", 
            "height": 88, 
            "hier_level": 16, 
            "human_hash": "android.widget.LinearLayout_X772_Y1856_W263_H88", 
            "index": "0", 
            "is_transformed": true, 
            "long-clickable": false, 
            "password": false, 
            "scrollable": false, 
            "selected": false, 
            "tag_name": "android.widget.LinearLayout", 
            "text": "LssLiveChat-TextPost", 
            "width": 263, 
            "x": 772, 
            "y": 1856
        }, 
        {
            "bounds": "[794,1878][838,1922]", 
            "checkable": false, 
            "checked": false, 
            "class": "android.widget.ImageView", 
            "clickable": false, 
            "enabled": true, 
            "focusable": false, 
            "focused": false, 
            "hash": "a+9kGBEQ6GMBYMA1+5iNDg==\n", 
            "height": 44, 
            "hier_level": 17, 
            "human_hash": "android.widget.ImageView_X794_Y1878_W44_H44", 
            "index": "0", 
            "is_transformed": true, 
            "long-clickable": false, 
            "password": false, 
            "resource-id": "com.reddit.frontpage.alpha:id/subreddit_icon", 
            "scrollable": false, 
            "selected": false, 
            "tag_name": "android.widget.ImageView", 
            "text": "", 
            "width": 44, 
            "x": 794, 
            "y": 1878
        }, 
        {
            "bounds": "[849,1878][1013,1922]", 
            "checkable": false, 
            "checked": false, 
            "class": "android.widget.TextView", 
            "clickable": false, 
            "enabled": true, 
            "focusable": false, 
            "focused": false, 
            "hash": "MZbntyHI4nZMmwNL1gbPbg==\n", 
            "height": 44, 
            "hier_level": 17, 
            "human_hash": "android.widget.TextView_X849_Y1878_W164_H44", 
            "index": "1", 
            "is_transformed": true, 
            "long-clickable": false, 
            "password": false, 
            "resource-id": "com.reddit.frontpage.alpha:id/post_title", 
            "scrollable": false, 
            "selected": false, 
            "tag_name": "android.widget.TextView", 
            "text": "LssLiveChat-TextPost", 
            "width": 164, 
            "x": 849, 
            "y": 1878
        }, 
        {
            "bounds": "[772,1966][1035,2054]", 
            "checkable": false, 
            "checked": false, 
            "class": "android.widget.LinearLayout", 
            "clickable": true, 
            "enabled": true, 
            "focusable": true, 
            "focused": false, 
            "hash": "Oe/q16D8U//gY4sfxZQhyQ==\n", 
            "height": 88, 
            "hier_level": 16, 
            "human_hash": "android.widget.LinearLayout_X772_Y1966_W263_H88", 
            "index": "1", 
            "is_transformed": true, 
            "long-clickable": false, 
            "password": false, 
            "scrollable": false, 
            "selected": false, 
            "tag_name": "android.widget.LinearLayout", 
            "text": "LssLiveChat-TextPost", 
            "width": 263, 
            "x": 772, 
            "y": 1966
        }, 
        {
            "bounds": "[794,1988][838,2032]", 
            "checkable": false, 
            "checked": false, 
            "class": "android.widget.ImageView", 
            "clickable": false, 
            "enabled": true, 
            "focusable": false, 
            "focused": false, 
            "hash": "TKZPKLIEz1TuQwsbAkazbQ==\n", 
            "height": 44, 
            "hier_level": 17, 
            "human_hash": "android.widget.ImageView_X794_Y1988_W44_H44", 
            "index": "0", 
            "is_transformed": true, 
            "long-clickable": false, 
            "password": false, 
            "resource-id": "com.reddit.frontpage.alpha:id/subreddit_icon", 
            "scrollable": false, 
            "selected": false, 
            "tag_name": "android.widget.ImageView", 
            "text": "", 
            "width": 44, 
            "x": 794, 
            "y": 1988
        }, 
        {
            "bounds": "[849,1988][1013,2032]", 
            "checkable": false, 
            "checked": false, 
            "class": "android.widget.TextView", 
            "clickable": false, 
            "enabled": true, 
            "focusable": false, 
            "focused": false, 
            "hash": "vHfq/cF4O4xlP26L7nUHbg==\n", 
            "height": 44, 
            "hier_level": 17, 
            "human_hash": "android.widget.TextView_X849_Y1988_W164_H44", 
            "index": "1", 
            "is_transformed": true, 
            "long-clickable": false, 
            "password": false, 
            "resource-id": "com.reddit.frontpage.alpha:id/post_title", 
            "scrollable": false, 
            "selected": false, 
            "tag_name": "android.widget.TextView", 
            "text": "LssLiveChat-TextPost", 
            "width": 164, 
            "x": 849, 
            "y": 1988
        }, 
        {
            "bounds": "[0,2093][1080,2236]", 
            "checkable": false, 
            "checked": false, 
            "class": "android.widget.LinearLayout", 
            "clickable": false, 
            "enabled": true, 
            "focusable": false, 
            "focused": false, 
            "hash": "q0yizU4E6B7UpGnqDajtCg==\n", 
            "height": 143, 
            "hier_level": 11, 
            "human_hash": "android.widget.LinearLayout_X0_Y2093_W1080_H143", 
            "index": "1", 
            "is_transformed": true, 
            "long-clickable": false, 
            "password": false, 
            "resource-id": "com.reddit.frontpage.alpha:id/bottom_nav", 
            "scrollable": false, 
            "selected": false, 
            "tag_name": "android.widget.LinearLayout", 
            "text": "2 1,188", 
            "width": 1080, 
            "x": 0, 
            "y": 2093
        }, 
        {
            "bounds": "[0,2093][216,2236]", 
            "checkable": false, 
            "checked": false, 
            "class": "android.view.ViewGroup", 
            "clickable": true, 
            "content-desc": "Home", 
            "enabled": true, 
            "focusable": true, 
            "focused": false, 
            "hash": "/+3yZ+6Dka1KoV+oBinTnQ==\n", 
            "height": 143, 
            "hier_level": 12, 
            "human_hash": "android.view.ViewGroup_X0_Y2093_W216_H143", 
            "index": "0", 
            "is_transformed": true, 
            "long-clickable": false, 
            "password": false, 
            "scrollable": false, 
            "selected": true, 
            "tag_name": "android.view.ViewGroup", 
            "text": "", 
            "width": 216, 
            "x": 0, 
            "y": 2093
        }, 
        {
            "bounds": "[75,2132][141,2198]", 
            "checkable": false, 
            "checked": false, 
            "class": "android.widget.ImageView", 
            "clickable": false, 
            "enabled": true, 
            "focusable": false, 
            "focused": false, 
            "hash": "p9KkW2fk+aVsf/PbcL2nAw==\n", 
            "height": 66, 
            "hier_level": 13, 
            "human_hash": "android.widget.ImageView_X75_Y2132_W66_H66", 
            "index": "0", 
            "is_transformed": true, 
            "long-clickable": false, 
            "password": false, 
            "resource-id": "com.reddit.frontpage.alpha:id/bottom_nav_item_icon", 
            "scrollable": false, 
            "selected": true, 
            "tag_name": "android.widget.ImageView", 
            "text": "", 
            "width": 66, 
            "x": 75, 
            "y": 2132
        }, 
        {
            "bounds": "[216,2093][432,2236]", 
            "checkable": false, 
            "checked": false, 
            "class": "android.view.ViewGroup", 
            "clickable": true, 
            "content-desc": "Browse", 
            "enabled": true, 
            "focusable": true, 
            "focused": false, 
            "hash": "OkVw577NsjkTpx41o35amg==\n", 
            "height": 143, 
            "hier_level": 12, 
            "human_hash": "android.view.ViewGroup_X216_Y2093_W216_H143", 
            "index": "1", 
            "is_transformed": true, 
            "long-clickable": false, 
            "password": false, 
            "scrollable": false, 
            "selected": false, 
            "tag_name": "android.view.ViewGroup", 
            "text": "", 
            "width": 216, 
            "x": 216, 
            "y": 2093
        }, 
        {
            "bounds": "[291,2132][357,2198]", 
            "checkable": false, 
            "checked": false, 
            "class": "android.widget.ImageView", 
            "clickable": false, 
            "enabled": true, 
            "focusable": false, 
            "focused": false, 
            "hash": "CuQ5wXezzdXW7fBWflnI7g==\n", 
            "height": 66, 
            "hier_level": 13, 
            "human_hash": "android.widget.ImageView_X291_Y2132_W66_H66", 
            "index": "0", 
            "is_transformed": true, 
            "long-clickable": false, 
            "password": false, 
            "resource-id": "com.reddit.frontpage.alpha:id/bottom_nav_item_icon", 
            "scrollable": false, 
            "selected": false, 
            "tag_name": "android.widget.ImageView", 
            "text": "", 
            "width": 66, 
            "x": 291, 
            "y": 2132
        }, 
        {
            "bounds": "[360,2135][377,2152]", 
            "checkable": false, 
            "checked": false, 
            "class": "android.widget.ImageView", 
            "clickable": false, 
            "enabled": true, 
            "focusable": false, 
            "focused": false, 
            "hash": "WziR1Jayqwe/6spD4TbktQ==\n", 
            "height": 17, 
            "hier_level": 13, 
            "human_hash": "android.widget.ImageView_X360_Y2135_W17_H17", 
            "index": "1", 
            "is_transformed": true, 
            "long-clickable": false, 
            "password": false, 
            "resource-id": "com.reddit.frontpage.alpha:id/bottom_nav_item_notification_no_number", 
            "scrollable": false, 
            "selected": false, 
            "tag_name": "android.widget.ImageView", 
            "text": "", 
            "width": 17, 
            "x": 360, 
            "y": 2135
        }, 
        {
            "bounds": "[432,2093][648,2236]", 
            "checkable": false, 
            "checked": false, 
            "class": "android.widget.LinearLayout", 
            "clickable": true, 
            "content-desc": "Post", 
            "enabled": true, 
            "focusable": true, 
            "focused": false, 
            "hash": "h+Cg+iNz+Z9yovkMlB8bgQ==\n", 
            "height": 143, 
            "hier_level": 12, 
            "human_hash": "android.widget.LinearLayout_X432_Y2093_W216_H143", 
            "index": "2", 
            "is_transformed": true, 
            "long-clickable": false, 
            "password": false, 
            "scrollable": false, 
            "selected": false, 
            "tag_name": "android.widget.LinearLayout", 
            "text": "", 
            "width": 216, 
            "x": 432, 
            "y": 2093
        }, 
        {
            "bounds": "[507,2131][573,2197]", 
            "checkable": false, 
            "checked": false, 
            "class": "android.widget.ImageView", 
            "clickable": false, 
            "enabled": true, 
            "focusable": false, 
            "focused": false, 
            "hash": "MQ2fwdY0Oap0UKF7pWE0lA==\n", 
            "height": 66, 
            "hier_level": 13, 
            "human_hash": "android.widget.ImageView_X507_Y2131_W66_H66", 
            "index": "0", 
            "is_transformed": true, 
            "long-clickable": false, 
            "password": false, 
            "resource-id": "com.reddit.frontpage.alpha:id/bottom_nav_item_icon", 
            "scrollable": false, 
            "selected": false, 
            "tag_name": "android.widget.ImageView", 
            "text": "", 
            "width": 66, 
            "x": 507, 
            "y": 2131
        }, 
        {
            "bounds": "[648,2093][864,2236]", 
            "checkable": false, 
            "checked": false, 
            "class": "android.view.ViewGroup", 
            "clickable": true, 
            "content-desc": "Chat", 
            "enabled": true, 
            "focusable": true, 
            "focused": false, 
            "hash": "PH1LSwOtsxhKNHYfPmQQeA==\n", 
            "height": 143, 
            "hier_level": 12, 
            "human_hash": "android.view.ViewGroup_X648_Y2093_W216_H143", 
            "index": "3", 
            "is_transformed": true, 
            "long-clickable": false, 
            "password": false, 
            "scrollable": false, 
            "selected": false, 
            "tag_name": "android.view.ViewGroup", 
            "text": "2", 
            "width": 216, 
            "x": 648, 
            "y": 2093
        }, 
        {
            "bounds": "[723,2132][789,2198]", 
            "checkable": false, 
            "checked": false, 
            "class": "android.widget.ImageView", 
            "clickable": false, 
            "enabled": true, 
            "focusable": false, 
            "focused": false, 
            "hash": "Dk/+g9NUwYvx/ewtIcd5JQ==\n", 
            "height": 66, 
            "hier_level": 13, 
            "human_hash": "android.widget.ImageView_X723_Y2132_W66_H66", 
            "index": "0", 
            "is_transformed": true, 
            "long-clickable": false, 
            "password": false, 
            "resource-id": "com.reddit.frontpage.alpha:id/bottom_nav_item_icon", 
            "scrollable": false, 
            "selected": false, 
            "tag_name": "android.widget.ImageView", 
            "text": "", 
            "width": 66, 
            "x": 723, 
            "y": 2132
        }, 
        {
            "bounds": "[775,2116][826,2170]", 
            "checkable": false, 
            "checked": false, 
            "class": "android.widget.TextView", 
            "clickable": false, 
            "enabled": true, 
            "focusable": false, 
            "focused": false, 
            "hash": "gq4y476c0XOSNbVAVjcLrA==\n", 
            "height": 54, 
            "hier_level": 13, 
            "human_hash": "android.widget.TextView_X775_Y2116_W51_H54", 
            "index": "1", 
            "is_transformed": true, 
            "long-clickable": false, 
            "password": false, 
            "resource-id": "com.reddit.frontpage.alpha:id/bottom_nav_item_notification", 
            "scrollable": false, 
            "selected": false, 
            "tag_name": "android.widget.TextView", 
            "text": "2", 
            "width": 51, 
            "x": 775, 
            "y": 2116
        }, 
        {
            "bounds": "[864,2093][1080,2236]", 
            "checkable": false, 
            "checked": false, 
            "class": "android.view.ViewGroup", 
            "clickable": true, 
            "content-desc": "Inbox", 
            "enabled": true, 
            "focusable": true, 
            "focused": false, 
            "hash": "kyCjxY5DVedfLzYOegd4CQ==\n", 
            "height": 143, 
            "hier_level": 12, 
            "human_hash": "android.view.ViewGroup_X864_Y2093_W216_H143", 
            "index": "4", 
            "is_transformed": true, 
            "long-clickable": false, 
            "password": false, 
            "scrollable": false, 
            "selected": false, 
            "tag_name": "android.view.ViewGroup", 
            "text": "1,188", 
            "width": 216, 
            "x": 864, 
            "y": 2093
        }, 
        {
            "bounds": "[939,2132][1005,2198]", 
            "checkable": false, 
            "checked": false, 
            "class": "android.widget.ImageView", 
            "clickable": false, 
            "enabled": true, 
            "focusable": false, 
            "focused": false, 
            "hash": "BZLUbC1Smp4FlUk+roYSFg==\n", 
            "height": 66, 
            "hier_level": 13, 
            "human_hash": "android.widget.ImageView_X939_Y2132_W66_H66", 
            "index": "0", 
            "is_transformed": true, 
            "long-clickable": false, 
            "password": false, 
            "resource-id": "com.reddit.frontpage.alpha:id/bottom_nav_item_icon", 
            "scrollable": false, 
            "selected": false, 
            "tag_name": "android.widget.ImageView", 
            "text": "", 
            "width": 66, 
            "x": 939, 
            "y": 2132
        }, 
        {
            "bounds": "[959,2116][1074,2170]", 
            "checkable": false, 
            "checked": false, 
            "class": "android.widget.TextView", 
            "clickable": false, 
            "enabled": true, 
            "focusable": false, 
            "focused": false, 
            "hash": "1NfW2+BLi5D6M/aq6WZCgA==\n", 
            "height": 54, 
            "hier_level": 13, 
            "human_hash": "android.widget.TextView_X959_Y2116_W115_H54", 
            "index": "1", 
            "is_transformed": true, 
            "long-clickable": false, 
            "password": false, 
            "resource-id": "com.reddit.frontpage.alpha:id/bottom_nav_item_notification", 
            "scrollable": false, 
            "selected": false, 
            "tag_name": "android.widget.TextView", 
            "text": "1,188", 
            "width": 115, 
            "x": 959, 
            "y": 2116
        }
    ], 
    "cpu": 0, 
    "jank": 0, 
    "mem": 0, 
    "net": 0, 
    "processed": false, 
    "timing": 0
}